{"formatVersion":13,"judgeLineList":[{"bpm":158.0,"judgeLineDisappearEvents":[{"easing":0,"end":0.0,"endTime":128.0,"start":1.0,"startTime":0.0},{"easing":6,"end":1.0,"endTime":256.0,"start":0.0,"startTime":128.0},{"easing":0,"end":1.0,"endTime":10368.0,"start":1.0,"startTime":256.0},{"easing":0,"end":0.0,"endTime":10496.0,"start":1.0,"startTime":10368.0},{"easing":0,"end":0.0,"endTime":1000000000.0,"start":0.0,"startTime":10496.0}],"judgeLineMoveXEvents":[{"easing":0,"end":0.5,"endTime":128.0,"start":0.5,"startTime":0.0},{"easing":0,"end":0.5,"endTime":256.0,"start":0.5,"startTime":128.0},{"easing":0,"end":0.5,"endTime":1888.0,"start":0.5,"startTime":256.0},{"easing":0,"end":0.5,"endTime":1920.0,"start":0.5,"startTime":1888.0},{"easing":0,"end":0.5,"endTime":2688.0,"start":0.5,"startTime":1920.0},{"easing":6,"end":0.47999999999999998,"endTime":2720.0,"start":0.5,"startTime":2688.0},{"easing":6,"end":0.5,"endTime":2752.0,"start":0.47999999999999998,"startTime":2720.0},{"easing":6,"end":0.52000000000000002,"endTime":2784.0,"start":0.5,"startTime":2752.0},{"easing":6,"end":0.5,"endTime":2816.0,"start":0.52000000000000002,"startTime":2784.0},{"easing":0,"end":0.5,"endTime":3968.0,"start":0.5,"startTime":2816.0},{"easing":30,"end":0.45465329999999998,"endTime":4061.0,"start":0.5,"startTime":3968.0},{"easing":19,"end":0.57316719999999999,"endTime":4150.0,"start":0.45465329999999998,"startTime":4061.0},{"easing":9,"end":0.5,"endTime":4224.0,"start":0.57316719999999999,"startTime":4150.0},{"easing":0,"end":0.5,"endTime":4448.0,"start":0.5,"startTime":4224.0},{"easing":0,"end":0.5,"endTime":4480.0,"start":0.5,"startTime":4448.0},{"easing":0,"end":0.5,"endTime":4960.0,"start":0.5,"startTime":4480.0},{"easing":0,"end":0.52000000000000002,"endTime":4962.0,"start":0.5,"startTime":4960.0},{"easing":0,"end":0.47999999999999998,"endTime":4964.0,"start":0.52000000000000002,"startTime":4962.0},{"easing":0,"end":0.51000000000000001,"endTime":4966.0,"start":0.47999999999999998,"startTime":4964.0},{"easing":0,"end":0.48999999999999999,"endTime":4968.0,"start":0.51000000000000001,"startTime":4966.0},{"easing":0,"end":0.505,"endTime":4970.0,"start":0.48999999999999999,"startTime":4968.0},{"easing":0,"end":0.495,"endTime":4972.0,"start":0.505,"startTime":4970.0},{"easing":0,"end":0.5,"endTime":4974.0,"start":0.495,"startTime":4972.0},{"easing":0,"end":0.5,"endTime":5216.0,"start":0.5,"startTime":4974.0},{"easing":0,"end":0.5,"endTime":7296.0,"start":0.5,"startTime":5216.0},{"easing":0,"end":0.5,"endTime":8320.0,"start":0.5,"startTime":7296.0},{"easing":0,"end":0.5,"endTime":8576.0,"start":0.5,"startTime":8320.0},{"easing":0,"end":0.5,"endTime":8800.0,"start":0.5,"startTime":8576.0},{"easing":0,"end":0.5,"endTime":8832.0,"start":0.5,"startTime":8800.0},{"easing":0,"end":0.5,"endTime":9344.0,"start":0.5,"startTime":8832.0},{"easing":0,"end":0.5,"endTime":9984.0,"start":0.5,"startTime":9344.0},{"easing":0,"end":0.5,"endTime":10240.0,"start":0.5,"startTime":9984.0},{"easing":0,"end":0.5,"endTime":10304.0,"start":0.5,"startTime":10240.0},{"easing":0,"end":0.5,"endTime":10368.0,"start":0.5,"startTime":10304.0},{"easing":0,"end":0.5,"endTime":10496.0,"start":0.5,"startTime":10368.0},{"easing":0,"end":0.5,"endTime":1000000000.0,"start":0.5,"startTime":10496.0}],"judgeLineMoveYEvents":[{"easing":0,"end":0.5,"endTime":128.0,"start":0.5,"startTime":0.0},{"easing":6,"end":0.20000000000000001,"endTime":256.0,"start":0.5,"startTime":128.0},{"easing":0,"end":0.20000000000000001,"endTime":1888.0,"start":0.20000000000000001,"startTime":256.0},{"easing":30,"end":0.24581175999999999,"endTime":1911.0,"start":0.20000000000000001,"startTime":1888.0},{"easing":17,"end":0.20000000000000001,"endTime":1920.0,"start":0.24581175999999999,"startTime":1911.0},{"easing":0,"end":0.20000000000000001,"endTime":2688.0,"start":0.20000000000000001,"startTime":1920.0},{"easing":0,"end":0.20000000000000001,"endTime":2816.0,"start":0.20000000000000001,"startTime":2688.0},{"easing":0,"end":0.20000000000000001,"endTime":3968.0,"start":0.20000000000000001,"startTime":2816.0},{"easing":0,"end":0.20000000000000001,"endTime":4224.0,"start":0.20000000000000001,"startTime":3968.0},{"easing":0,"end":0.20000000000000001,"endTime":4448.0,"start":0.20000000000000001,"startTime":4224.0},{"easing":30,"end":0.24581175999999999,"endTime":4471.0,"start":0.20000000000000001,"startTime":4448.0},{"easing":17,"end":0.20000000000000001,"endTime":4480.0,"start":0.24581175999999999,"startTime":4471.0},{"easing":0,"end":0.20000000000000001,"endTime":4960.0,"start":0.20000000000000001,"startTime":4480.0},{"easing":0,"end":0.20000000000000001,"endTime":4974.0,"start":0.20000000000000001,"startTime":4960.0},{"easing":0,"end":0.20000000000000001,"endTime":5216.0,"start":0.20000000000000001,"startTime":4974.0},{"easing":30,"end":0.24581175999999999,"endTime":5239.0,"start":0.20000000000000001,"startTime":5216.0},{"easing":3,"end":0.15263814000000001,"endTime":5258.0,"start":0.24581175999999999,"startTime":5239.0},{"easing":29,"end":0.18349937999999999,"endTime":5278.0,"start":0.15263814000000001,"startTime":5258.0},{"easing":0,"end":0.20000000000000001,"endTime":5280.0,"start":0.18349937999999999,"startTime":5278.0},{"easing":30,"end":0.15418825,"endTime":5303.0,"start":0.20000000000000001,"startTime":5280.0},{"easing":17,"end":0.20000000000000001,"endTime":5312.0,"start":0.15418825,"startTime":5303.0},{"easing":30,"end":0.15418825,"endTime":5335.0,"start":0.20000000000000001,"startTime":5312.0},{"easing":17,"end":0.20000000000000001,"endTime":5344.0,"start":0.15418825,"startTime":5335.0},{"easing":30,"end":0.15418825,"endTime":5367.0,"start":0.20000000000000001,"startTime":5344.0},{"easing":17,"end":0.20000000000000001,"endTime":5376.0,"start":0.15418825,"startTime":5367.0},{"easing":30,"end":0.15418825,"endTime":5399.0,"start":0.20000000000000001,"startTime":5376.0},{"easing":17,"end":0.20000000000000001,"endTime":5408.0,"start":0.15418825,"startTime":5399.0},{"easing":30,"end":0.15418825,"endTime":5431.0,"start":0.20000000000000001,"startTime":5408.0},{"easing":17,"end":0.20000000000000001,"endTime":5440.0,"start":0.15418825,"startTime":5431.0},{"easing":30,"end":0.15418825,"endTime":5463.0,"start":0.20000000000000001,"startTime":5440.0},{"easing":17,"end":0.20000000000000001,"endTime":5472.0,"start":0.15418825,"startTime":5463.0},{"easing":30,"end":0.15418825,"endTime":5495.0,"start":0.20000000000000001,"startTime":5472.0},{"easing":17,"end":0.20000000000000001,"endTime":5504.0,"start":0.15418825,"startTime":5495.0},{"easing":30,"end":0.15418825,"endTime":5527.0,"start":0.20000000000000001,"startTime":5504.0},{"easing":17,"end":0.20000000000000001,"endTime":5536.0,"start":0.15418825,"startTime":5527.0},{"easing":30,"end":0.15418825,"endTime":5559.0,"start":0.20000000000000001,"startTime":5536.0},{"easing":17,"end":0.20000000000000001,"endTime":5568.0,"start":0.15418825,"startTime":5559.0},{"easing":30,"end":0.15418825,"endTime":5591.0,"start":0.20000000000000001,"startTime":5568.0},{"easing":17,"end":0.20000000000000001,"endTime":5600.0,"start":0.15418825,"startTime":5591.0},{"easing":30,"end":0.15418825,"endTime":5623.0,"start":0.20000000000000001,"startTime":5600.0},{"easing":17,"end":0.20000000000000001,"endTime":5632.0,"start":0.15418825,"startTime":5623.0},{"easing":30,"end":0.15418825,"endTime":5655.0,"start":0.20000000000000001,"startTime":5632.0},{"easing":17,"end":0.20000000000000001,"endTime":5664.0,"start":0.15418825,"startTime":5655.0},{"easing":30,"end":0.15418825,"endTime":5687.0,"start":0.20000000000000001,"startTime":5664.0},{"easing":17,"end":0.20000000000000001,"endTime":5696.0,"start":0.15418825,"startTime":5687.0},{"easing":30,"end":0.15418825,"endTime":5719.0,"start":0.20000000000000001,"startTime":5696.0},{"easing":17,"end":0.20000000000000001,"endTime":5728.0,"start":0.15418825,"startTime":5719.0},{"easing":14,"end":0.1500013,"endTime":5752.0,"start":0.20000000000000001,"startTime":5728.0},{"easing":5,"end":0.20000000000000001,"endTime":6016.0,"start":0.1500013,"startTime":5752.0},{"easing":30,"end":0.15418825,"endTime":6039.0,"start":0.20000000000000001,"startTime":6016.0},{"easing":17,"end":0.20000000000000001,"endTime":6048.0,"start":0.15418825,"startTime":6039.0},{"easing":30,"end":0.15418825,"endTime":6071.0,"start":0.20000000000000001,"startTime":6048.0},{"easing":17,"end":0.20000000000000001,"endTime":6080.0,"start":0.15418825,"startTime":6071.0},{"easing":30,"end":0.15418825,"endTime":6103.0,"start":0.20000000000000001,"startTime":6080.0},{"easing":17,"end":0.20000000000000001,"endTime":6112.0,"start":0.15418825,"startTime":6103.0},{"easing":30,"end":0.15418825,"endTime":6135.0,"start":0.20000000000000001,"startTime":6112.0},{"easing":17,"end":0.20000000000000001,"endTime":6144.0,"start":0.15418825,"startTime":6135.0},{"easing":30,"end":0.15418825,"endTime":6167.0,"start":0.20000000000000001,"startTime":6144.0},{"easing":17,"end":0.20000000000000001,"endTime":6176.0,"start":0.15418825,"startTime":6167.0},{"easing":30,"end":0.15418825,"endTime":6199.0,"start":0.20000000000000001,"startTime":6176.0},{"easing":17,"end":0.20000000000000001,"endTime":6208.0,"start":0.15418825,"startTime":6199.0},{"easing":30,"end":0.15418825,"endTime":6231.0,"start":0.20000000000000001,"startTime":6208.0},{"easing":17,"end":0.20000000000000001,"endTime":6240.0,"start":0.15418825,"startTime":6231.0},{"easing":30,"end":0.15418825,"endTime":6263.0,"start":0.20000000000000001,"startTime":6240.0},{"easing":10,"end":0.76663999999999999,"endTime":6848.0,"start":0.15418825,"startTime":6263.0},{"easing":19,"end":0.21878001,"endTime":7120.0,"start":0.76663999999999999,"startTime":6848.0},{"easing":6,"end":0.19931225,"endTime":7191.0,"start":0.21878001,"startTime":7120.0},{"easing":1,"end":0.14999999999999999,"endTime":7264.0,"start":0.19931225,"startTime":7191.0},{"easing":6,"end":0.20000000000000001,"endTime":7296.0,"start":0.14999999999999999,"startTime":7264.0},{"easing":0,"end":0.20000000000000001,"endTime":8320.0,"start":0.20000000000000001,"startTime":7296.0},{"easing":6,"end":0.80000000000000004,"endTime":8448.0,"start":0.20000000000000001,"startTime":8320.0},{"easing":6,"end":0.20000000000000001,"endTime":8576.0,"start":0.80000000000000004,"startTime":8448.0},{"easing":0,"end":0.20000000000000001,"endTime":8800.0,"start":0.20000000000000001,"startTime":8576.0},{"easing":30,"end":0.24581175999999999,"endTime":8823.0,"start":0.20000000000000001,"startTime":8800.0},{"easing":17,"end":0.20000000000000001,"endTime":8832.0,"start":0.24581175999999999,"startTime":8823.0},{"easing":0,"end":0.20000000000000001,"endTime":9344.0,"start":0.20000000000000001,"startTime":8832.0},{"easing":30,"end":0.15418825,"endTime":9367.0,"start":0.20000000000000001,"startTime":9344.0},{"easing":17,"end":0.20000000000000001,"endTime":9376.0,"start":0.15418825,"startTime":9367.0},{"easing":30,"end":0.15418825,"endTime":9399.0,"start":0.20000000000000001,"startTime":9376.0},{"easing":17,"end":0.20000000000000001,"endTime":9408.0,"start":0.15418825,"startTime":9399.0},{"easing":30,"end":0.15418825,"endTime":9431.0,"start":0.20000000000000001,"startTime":9408.0},{"easing":17,"end":0.20000000000000001,"endTime":9440.0,"start":0.15418825,"startTime":9431.0},{"easing":30,"end":0.15418825,"endTime":9463.0,"start":0.20000000000000001,"startTime":9440.0},{"easing":17,"end":0.20000000000000001,"endTime":9472.0,"start":0.15418825,"startTime":9463.0},{"easing":30,"end":0.15418825,"endTime":9495.0,"start":0.20000000000000001,"startTime":9472.0},{"easing":17,"end":0.20000000000000001,"endTime":9504.0,"start":0.15418825,"startTime":9495.0},{"easing":30,"end":0.15418825,"endTime":9527.0,"start":0.20000000000000001,"startTime":9504.0},{"easing":17,"end":0.20000000000000001,"endTime":9536.0,"start":0.15418825,"startTime":9527.0},{"easing":30,"end":0.15418825,"endTime":9559.0,"start":0.20000000000000001,"startTime":9536.0},{"easing":17,"end":0.20000000000000001,"endTime":9568.0,"start":0.15418825,"startTime":9559.0},{"easing":30,"end":0.15418825,"endTime":9591.0,"start":0.20000000000000001,"startTime":9568.0},{"easing":17,"end":0.20000000000000001,"endTime":9600.0,"start":0.15418825,"startTime":9591.0},{"easing":30,"end":0.15418825,"endTime":9623.0,"start":0.20000000000000001,"startTime":9600.0},{"easing":17,"end":0.20000000000000001,"endTime":9632.0,"start":0.15418825,"startTime":9623.0},{"easing":30,"end":0.15418825,"endTime":9655.0,"start":0.20000000000000001,"startTime":9632.0},{"easing":17,"end":0.20000000000000001,"endTime":9664.0,"start":0.15418825,"startTime":9655.0},{"easing":30,"end":0.15418825,"endTime":9687.0,"start":0.20000000000000001,"startTime":9664.0},{"easing":17,"end":0.20000000000000001,"endTime":9696.0,"start":0.15418825,"startTime":9687.0},{"easing":30,"end":0.15418825,"endTime":9719.0,"start":0.20000000000000001,"startTime":9696.0},{"easing":17,"end":0.20000000000000001,"endTime":9728.0,"start":0.15418825,"startTime":9719.0},{"easing":30,"end":0.15418825,"endTime":9751.0,"start":0.20000000000000001,"startTime":9728.0},{"easing":17,"end":0.20000000000000001,"endTime":9760.0,"start":0.15418825,"startTime":9751.0},{"easing":30,"end":0.15418825,"endTime":9783.0,"start":0.20000000000000001,"startTime":9760.0},{"easing":17,"end":0.20000000000000001,"endTime":9792.0,"start":0.15418825,"startTime":9783.0},{"easing":30,"end":0.15418825,"endTime":9815.0,"start":0.20000000000000001,"startTime":9792.0},{"easing":17,"end":0.20000000000000001,"endTime":9824.0,"start":0.15418825,"startTime":9815.0},{"easing":30,"end":0.15418825,"endTime":9847.0,"start":0.20000000000000001,"startTime":9824.0},{"easing":6,"end":0.29999999999999999,"endTime":9920.0,"start":0.15418825,"startTime":9847.0},{"easing":6,"end":0.20000000000000001,"endTime":9984.0,"start":0.29999999999999999,"startTime":9920.0},{"easing":0,"end":0.20000000000000001,"endTime":10240.0,"start":0.20000000000000001,"startTime":9984.0},{"easing":5,"end":0.5,"endTime":10304.0,"start":0.20000000000000001,"startTime":10240.0},{"easing":0,"end":0.5,"endTime":10368.0,"start":0.5,"startTime":10304.0},{"easing":6,"end":0.0,"endTime":10496.0,"start":0.5,"startTime":10368.0},{"easing":0,"end":0.0,"endTime":1000000000.0,"start":0.0,"startTime":10496.0}],"judgeLineRotateEvents":[{"easing":0,"end":360.0,"endTime":128.0,"start":360.0,"startTime":0.0},{"easing":6,"end":0.0,"endTime":256.0,"start":360.0,"startTime":128.0},{"easing":30,"end":4.5346704000000004,"endTime":349.0,"start":0.0,"startTime":256.0},{"easing":19,"end":-4.7679014000000004,"endTime":425.0,"start":4.5346704000000004,"startTime":349.0},{"easing":13,"end":3.3750513,"endTime":522.0,"start":-4.7679014000000004,"startTime":425.0},{"easing":6,"end":5.0,"endTime":544.0,"start":3.3750513,"startTime":522.0},{"easing":6,"end":-2.5,"endTime":576.0,"start":5.0,"startTime":544.0},{"easing":6,"end":2.5,"endTime":608.0,"start":-2.5,"startTime":576.0},{"easing":6,"end":-5.0,"endTime":640.0,"start":2.5,"startTime":608.0},{"easing":6,"end":7.4937699999999996,"endTime":774.0,"start":-5.0,"startTime":640.0},{"easing":5,"end":-4.5811763000000001,"endTime":841.0,"start":7.4937699999999996,"startTime":774.0},{"easing":30,"end":-4.9669885999999996,"endTime":851.0,"start":-4.5811763000000001,"startTime":841.0},{"easing":1,"end":-2.3178860000000001,"endTime":861.0,"start":-4.9669885999999996,"startTime":851.0},{"easing":0,"end":-0.87986379999999997,"endTime":863.0,"start":-2.3178860000000001,"startTime":861.0},{"easing":25,"end":5.0,"endTime":865.0,"start":-0.87986379999999997,"startTime":863.0},{"easing":6,"end":0.0,"endTime":896.0,"start":5.0,"startTime":865.0},{"easing":0,"end":0.0,"endTime":928.0,"start":0.0,"startTime":896.0},{"easing":10,"end":-3.0,"endTime":992.0,"start":0.0,"startTime":928.0},{"easing":10,"end":-6.0,"endTime":1056.0,"start":-3.0,"startTime":992.0},{"easing":10,"end":-9.0,"endTime":1088.0,"start":-6.0,"startTime":1056.0},{"easing":14,"end":4.921875,"endTime":1128.0,"start":-9.0,"startTime":1088.0},{"easing":1,"end":0.0,"endTime":1152.0,"start":4.921875,"startTime":1128.0},{"easing":0,"end":0.0,"endTime":1184.0,"start":0.0,"startTime":1152.0},{"easing":10,"end":3.0,"endTime":1248.0,"start":0.0,"startTime":1184.0},{"easing":10,"end":6.0,"endTime":1312.0,"start":3.0,"startTime":1248.0},{"easing":10,"end":9.0,"endTime":1344.0,"start":6.0,"startTime":1312.0},{"easing":14,"end":-4.921875,"endTime":1384.0,"start":9.0,"startTime":1344.0},{"easing":19,"end":4.70573,"endTime":1436.0,"start":-4.921875,"startTime":1384.0},{"easing":10,"end":7.5,"endTime":1536.0,"start":4.70573,"startTime":1436.0},{"easing":10,"end":0.0,"endTime":1664.0,"start":7.5,"startTime":1536.0},{"easing":10,"end":-7.5,"endTime":1792.0,"start":0.0,"startTime":1664.0},{"easing":10,"end":0.0,"endTime":1887.0,"start":-7.5,"startTime":1792.0},{"easing":0,"end":0.0,"endTime":1920.0,"start":0.0,"startTime":1887.0},{"easing":30,"end":-4.5346704000000004,"endTime":2013.0,"start":0.0,"startTime":1920.0},{"easing":19,"end":4.7679014000000004,"endTime":2089.0,"start":-4.5346704000000004,"startTime":2013.0},{"easing":29,"end":1.8265734,"endTime":2167.0,"start":4.7679014000000004,"startTime":2089.0},{"easing":2,"end":-4.9745736000000003,"endTime":2229.0,"start":1.8265734,"startTime":2167.0},{"easing":5,"end":2.4696264000000001,"endTime":2317.0,"start":-4.9745736000000003,"startTime":2229.0},{"easing":30,"end":4.7679014000000004,"endTime":2391.0,"start":2.4696264000000001,"startTime":2317.0},{"easing":3,"end":-4.9061940000000002,"endTime":2479.0,"start":4.7679014000000004,"startTime":2391.0},{"easing":6,"end":-5.0,"endTime":2496.0,"start":-4.9061940000000002,"startTime":2479.0},{"easing":6,"end":0.0,"endTime":2560.0,"start":-5.0,"startTime":2496.0},{"easing":6,"end":5.0,"endTime":2624.0,"start":0.0,"startTime":2560.0},{"easing":6,"end":0.0,"endTime":2688.0,"start":5.0,"startTime":2624.0},{"easing":0,"end":0.0,"endTime":2816.0,"start":0.0,"startTime":2688.0},{"easing":6,"end":5.0,"endTime":2848.0,"start":0.0,"startTime":2816.0},{"easing":6,"end":-4.0,"endTime":2880.0,"start":5.0,"startTime":2848.0},{"easing":6,"end":3.0,"endTime":2896.0,"start":-4.0,"startTime":2880.0},{"easing":6,"end":-2.0,"endTime":2912.0,"start":3.0,"startTime":2896.0},{"easing":6,"end":1.0,"endTime":2928.0,"start":-2.0,"startTime":2912.0},{"easing":6,"end":0.0,"endTime":2944.0,"start":1.0,"startTime":2928.0},{"easing":14,"end":7.5,"endTime":3072.0,"start":0.0,"startTime":2944.0},{"easing":6,"end":-5.0,"endTime":3168.0,"start":7.5,"startTime":3072.0},{"easing":6,"end":5.0,"endTime":3200.0,"start":-5.0,"startTime":3168.0},{"easing":14,"end":-5.0,"endTime":3328.0,"start":5.0,"startTime":3200.0},{"easing":6,"end":5.0,"endTime":3424.0,"start":-5.0,"startTime":3328.0},{"easing":6,"end":0.0,"endTime":3456.0,"start":5.0,"startTime":3424.0},{"easing":30,"end":4.5346704000000004,"endTime":3549.0,"start":0.0,"startTime":3456.0},{"easing":19,"end":-4.7679014000000004,"endTime":3625.0,"start":4.5346704000000004,"startTime":3549.0},{"easing":29,"end":-1.8265734,"endTime":3703.0,"start":-4.7679014000000004,"startTime":3625.0},{"easing":2,"end":4.9745736000000003,"endTime":3765.0,"start":-1.8265734,"startTime":3703.0},{"easing":5,"end":-2.1519917999999998,"endTime":3851.0,"start":4.9745736000000003,"startTime":3765.0},{"easing":30,"end":-2.9332302000000001,"endTime":3881.0,"start":-2.1519917999999998,"startTime":3851.0},{"easing":1,"end":0.0,"endTime":3904.0,"start":-2.9332302000000001,"startTime":3881.0},{"easing":0,"end":3.0,"endTime":3912.0,"start":0.0,"startTime":3904.0},{"easing":6,"end":0.0,"endTime":3936.0,"start":3.0,"startTime":3912.0},{"easing":0,"end":-3.0,"endTime":3944.0,"start":0.0,"startTime":3936.0},{"easing":6,"end":0.0,"endTime":3968.0,"start":-3.0,"startTime":3944.0},{"easing":0,"end":0.0,"endTime":4224.0,"start":0.0,"startTime":3968.0},{"easing":6,"end":180.0,"endTime":4352.0,"start":0.0,"startTime":4224.0},{"easing":6,"end":360.0,"endTime":4448.0,"start":180.0,"startTime":4352.0},{"easing":0,"end":0.0,"endTime":4512.0,"start":0.0,"startTime":4448.0},{"easing":0,"end":5.0,"endTime":4513.0,"start":0.0,"startTime":4512.0},{"easing":10,"end":0.0,"endTime":4576.0,"start":5.0,"startTime":4513.0},{"easing":0,"end":-5.0,"endTime":4577.0,"start":0.0,"startTime":4576.0},{"easing":10,"end":0.0,"endTime":4640.0,"start":-5.0,"startTime":4577.0},{"easing":0,"end":5.0,"endTime":4641.0,"start":0.0,"startTime":4640.0},{"easing":10,"end":0.0,"endTime":4704.0,"start":5.0,"startTime":4641.0},{"easing":0,"end":-3.0,"endTime":4705.0,"start":0.0,"startTime":4704.0},{"easing":10,"end":0.0,"endTime":4736.0,"start":-3.0,"startTime":4705.0},{"easing":30,"end":6.8020053000000003,"endTime":4829.0,"start":0.0,"startTime":4736.0},{"easing":0,"end":6.3753723999999998,"endTime":4834.0,"start":6.8020053000000003,"startTime":4829.0},{"easing":0,"end":5.6685939999999997,"endTime":4840.0,"start":6.3753723999999998,"startTime":4834.0},{"easing":0,"end":4.5291930000000002,"endTime":4847.0,"start":5.6685939999999997,"startTime":4840.0},{"easing":0,"end":2.7398600000000002,"endTime":4855.0,"start":4.5291930000000002,"startTime":4847.0},{"easing":2,"end":-4.9669885999999996,"endTime":4903.0,"start":2.7398600000000002,"startTime":4855.0},{"easing":9,"end":0.0,"endTime":4960.0,"start":-4.9669885999999996,"startTime":4903.0},{"easing":0,"end":360.0,"endTime":4992.0,"start":360.0,"startTime":4960.0},{"easing":14,"end":-5.0,"endTime":5184.0,"start":360.0,"startTime":4992.0},{"easing":30,"end":1.6439794999999999,"endTime":5209.0,"start":-5.0,"startTime":5184.0},{"easing":0,"end":1.3500205000000001,"endTime":5211.0,"start":1.6439794999999999,"startTime":5209.0},{"easing":0,"end":0.92715440000000005,"endTime":5213.0,"start":1.3500205000000001,"startTime":5211.0},{"easing":0,"end":0.35194552000000001,"endTime":5215.0,"start":0.92715440000000005,"startTime":5213.0},{"easing":0,"end":0.0,"endTime":5216.0,"start":0.35194552000000001,"startTime":5215.0},{"easing":0,"end":0.0,"endTime":6272.0,"start":0.0,"startTime":5216.0},{"easing":6,"end":180.0,"endTime":6784.0,"start":0.0,"startTime":6272.0},{"easing":3,"end":360.0,"endTime":7168.0,"start":180.0,"startTime":6784.0},{"easing":0,"end":0.0,"endTime":7328.0,"start":0.0,"startTime":7168.0},{"easing":30,"end":4.5811763000000001,"endTime":7374.0,"start":0.0,"startTime":7328.0},{"easing":0,"end":4.375,"endTime":7376.0,"start":4.5811763000000001,"startTime":7374.0},{"easing":0,"end":3.9531906000000001,"endTime":7379.0,"start":4.375,"startTime":7376.0},{"easing":0,"end":3.3750513,"endTime":7382.0,"start":3.9531906000000001,"startTime":7379.0},{"easing":0,"end":2.3178860000000001,"endTime":7386.0,"start":3.3750513,"startTime":7382.0},{"easing":0,"end":0.87986379999999997,"endTime":7390.0,"start":2.3178860000000001,"startTime":7386.0},{"easing":0,"end":0.0,"endTime":7392.0,"start":0.87986379999999997,"startTime":7390.0},{"easing":30,"end":4.5811763000000001,"endTime":7438.0,"start":0.0,"startTime":7392.0},{"easing":0,"end":4.375,"endTime":7440.0,"start":4.5811763000000001,"startTime":7438.0},{"easing":0,"end":3.9531906000000001,"endTime":7443.0,"start":4.375,"startTime":7440.0},{"easing":0,"end":3.3750513,"endTime":7446.0,"start":3.9531906000000001,"startTime":7443.0},{"easing":0,"end":2.3178860000000001,"endTime":7450.0,"start":3.3750513,"startTime":7446.0},{"easing":0,"end":0.87986379999999997,"endTime":7454.0,"start":2.3178860000000001,"startTime":7450.0},{"easing":0,"end":0.0,"endTime":7456.0,"start":0.87986379999999997,"startTime":7454.0},{"easing":30,"end":4.5811763000000001,"endTime":7502.0,"start":0.0,"startTime":7456.0},{"easing":0,"end":4.375,"endTime":7504.0,"start":4.5811763000000001,"startTime":7502.0},{"easing":0,"end":3.9531906000000001,"endTime":7507.0,"start":4.375,"startTime":7504.0},{"easing":0,"end":3.3750513,"endTime":7510.0,"start":3.9531906000000001,"startTime":7507.0},{"easing":0,"end":2.3178860000000001,"endTime":7514.0,"start":3.3750513,"startTime":7510.0},{"easing":0,"end":0.87986379999999997,"endTime":7518.0,"start":2.3178860000000001,"startTime":7514.0},{"easing":0,"end":0.0,"endTime":7520.0,"start":0.87986379999999997,"startTime":7518.0},{"easing":30,"end":4.5811763000000001,"endTime":7566.0,"start":0.0,"startTime":7520.0},{"easing":0,"end":4.375,"endTime":7568.0,"start":4.5811763000000001,"startTime":7566.0},{"easing":0,"end":3.9531906000000001,"endTime":7571.0,"start":4.375,"startTime":7568.0},{"easing":0,"end":3.3750513,"endTime":7574.0,"start":3.9531906000000001,"startTime":7571.0},{"easing":0,"end":2.3178860000000001,"endTime":7578.0,"start":3.3750513,"startTime":7574.0},{"easing":0,"end":0.87986379999999997,"endTime":7582.0,"start":2.3178860000000001,"startTime":7578.0},{"easing":0,"end":0.0,"endTime":7584.0,"start":0.87986379999999997,"startTime":7582.0},{"easing":30,"end":4.5811763000000001,"endTime":7630.0,"start":0.0,"startTime":7584.0},{"easing":0,"end":4.375,"endTime":7632.0,"start":4.5811763000000001,"startTime":7630.0},{"easing":0,"end":3.9531906000000001,"endTime":7635.0,"start":4.375,"startTime":7632.0},{"easing":0,"end":3.3750513,"endTime":7638.0,"start":3.9531906000000001,"startTime":7635.0},{"easing":0,"end":2.3178860000000001,"endTime":7642.0,"start":3.3750513,"startTime":7638.0},{"easing":0,"end":0.87986379999999997,"endTime":7646.0,"start":2.3178860000000001,"startTime":7642.0},{"easing":0,"end":0.0,"endTime":7648.0,"start":0.87986379999999997,"startTime":7646.0},{"easing":30,"end":4.5811763000000001,"endTime":7694.0,"start":0.0,"startTime":7648.0},{"easing":0,"end":4.375,"endTime":7696.0,"start":4.5811763000000001,"startTime":7694.0},{"easing":0,"end":3.9531906000000001,"endTime":7699.0,"start":4.375,"startTime":7696.0},{"easing":0,"end":3.3750513,"endTime":7702.0,"start":3.9531906000000001,"startTime":7699.0},{"easing":0,"end":2.3178860000000001,"endTime":7706.0,"start":3.3750513,"startTime":7702.0},{"easing":0,"end":0.87986379999999997,"endTime":7710.0,"start":2.3178860000000001,"startTime":7706.0},{"easing":0,"end":0.0,"endTime":7712.0,"start":0.87986379999999997,"startTime":7710.0},{"easing":30,"end":4.5811763000000001,"endTime":7758.0,"start":0.0,"startTime":7712.0},{"easing":0,"end":4.375,"endTime":7760.0,"start":4.5811763000000001,"startTime":7758.0},{"easing":0,"end":3.9531906000000001,"endTime":7763.0,"start":4.375,"startTime":7760.0},{"easing":0,"end":3.3750513,"endTime":7766.0,"start":3.9531906000000001,"startTime":7763.0},{"easing":0,"end":2.3178860000000001,"endTime":7770.0,"start":3.3750513,"startTime":7766.0},{"easing":0,"end":0.87986379999999997,"endTime":7774.0,"start":2.3178860000000001,"startTime":7770.0},{"easing":0,"end":0.0,"endTime":7776.0,"start":0.87986379999999997,"startTime":7774.0},{"easing":6,"end":5.0,"endTime":7808.0,"start":0.0,"startTime":7776.0},{"easing":6,"end":0.0,"endTime":7840.0,"start":5.0,"startTime":7808.0},{"easing":30,"end":-4.5811763000000001,"endTime":7886.0,"start":0.0,"startTime":7840.0},{"easing":0,"end":-4.375,"endTime":7888.0,"start":-4.5811763000000001,"startTime":7886.0},{"easing":0,"end":-3.9531906000000001,"endTime":7891.0,"start":-4.375,"startTime":7888.0},{"easing":0,"end":-3.3750513,"endTime":7894.0,"start":-3.9531906000000001,"startTime":7891.0},{"easing":0,"end":-2.3178860000000001,"endTime":7898.0,"start":-3.3750513,"startTime":7894.0},{"easing":0,"end":-0.87986379999999997,"endTime":7902.0,"start":-2.3178860000000001,"startTime":7898.0},{"easing":0,"end":0.0,"endTime":7904.0,"start":-0.87986379999999997,"startTime":7902.0},{"easing":30,"end":-4.5811763000000001,"endTime":7950.0,"start":0.0,"startTime":7904.0},{"easing":0,"end":-4.375,"endTime":7952.0,"start":-4.5811763000000001,"startTime":7950.0},{"easing":0,"end":-3.9531906000000001,"endTime":7955.0,"start":-4.375,"startTime":7952.0},{"easing":0,"end":-3.3750513,"endTime":7958.0,"start":-3.9531906000000001,"startTime":7955.0},{"easing":0,"end":-2.3178860000000001,"endTime":7962.0,"start":-3.3750513,"startTime":7958.0},{"easing":0,"end":-0.87986379999999997,"endTime":7966.0,"start":-2.3178860000000001,"startTime":7962.0},{"easing":0,"end":0.0,"endTime":7968.0,"start":-0.87986379999999997,"startTime":7966.0},{"easing":30,"end":-4.5811763000000001,"endTime":8014.0,"start":0.0,"startTime":7968.0},{"easing":0,"end":-4.375,"endTime":8016.0,"start":-4.5811763000000001,"startTime":8014.0},{"easing":0,"end":-3.9531906000000001,"endTime":8019.0,"start":-4.375,"startTime":8016.0},{"easing":0,"end":-3.3750513,"endTime":8022.0,"start":-3.9531906000000001,"startTime":8019.0},{"easing":0,"end":-2.3178860000000001,"endTime":8026.0,"start":-3.3750513,"startTime":8022.0},{"easing":0,"end":-0.87986379999999997,"endTime":8030.0,"start":-2.3178860000000001,"startTime":8026.0},{"easing":0,"end":0.0,"endTime":8032.0,"start":-0.87986379999999997,"startTime":8030.0},{"easing":30,"end":-4.5811763000000001,"endTime":8078.0,"start":0.0,"startTime":8032.0},{"easing":0,"end":-4.375,"endTime":8080.0,"start":-4.5811763000000001,"startTime":8078.0},{"easing":0,"end":-3.9531906000000001,"endTime":8083.0,"start":-4.375,"startTime":8080.0},{"easing":0,"end":-3.3750513,"endTime":8086.0,"start":-3.9531906000000001,"startTime":8083.0},{"easing":0,"end":-2.3178860000000001,"endTime":8090.0,"start":-3.3750513,"startTime":8086.0},{"easing":0,"end":-0.87986379999999997,"endTime":8094.0,"start":-2.3178860000000001,"startTime":8090.0},{"easing":0,"end":0.0,"endTime":8096.0,"start":-0.87986379999999997,"startTime":8094.0},{"easing":30,"end":-4.5811763000000001,"endTime":8142.0,"start":0.0,"startTime":8096.0},{"easing":0,"end":-4.375,"endTime":8144.0,"start":-4.5811763000000001,"startTime":8142.0},{"easing":0,"end":-3.9531906000000001,"endTime":8147.0,"start":-4.375,"startTime":8144.0},{"easing":0,"end":-3.3750513,"endTime":8150.0,"start":-3.9531906000000001,"startTime":8147.0},{"easing":0,"end":-2.3178860000000001,"endTime":8154.0,"start":-3.3750513,"startTime":8150.0},{"easing":0,"end":-0.87986379999999997,"endTime":8158.0,"start":-2.3178860000000001,"startTime":8154.0},{"easing":0,"end":0.0,"endTime":8160.0,"start":-0.87986379999999997,"startTime":8158.0},{"easing":30,"end":-4.5811763000000001,"endTime":8206.0,"start":0.0,"startTime":8160.0},{"easing":0,"end":-4.375,"endTime":8208.0,"start":-4.5811763000000001,"startTime":8206.0},{"easing":0,"end":-3.9531906000000001,"endTime":8211.0,"start":-4.375,"startTime":8208.0},{"easing":0,"end":-3.3750513,"endTime":8214.0,"start":-3.9531906000000001,"startTime":8211.0},{"easing":0,"end":-2.3178860000000001,"endTime":8218.0,"start":-3.3750513,"startTime":8214.0},{"easing":0,"end":-0.87986379999999997,"endTime":8222.0,"start":-2.3178860000000001,"startTime":8218.0},{"easing":0,"end":0.0,"endTime":8224.0,"start":-0.87986379999999997,"startTime":8222.0},{"easing":30,"end":-4.5811763000000001,"endTime":8270.0,"start":0.0,"startTime":8224.0},{"easing":0,"end":-4.375,"endTime":8272.0,"start":-4.5811763000000001,"startTime":8270.0},{"easing":0,"end":-3.9531906000000001,"endTime":8275.0,"start":-4.375,"startTime":8272.0},{"easing":0,"end":-3.3750513,"endTime":8278.0,"start":-3.9531906000000001,"startTime":8275.0},{"easing":0,"end":-2.3178860000000001,"endTime":8282.0,"start":-3.3750513,"startTime":8278.0},{"easing":18,"end":1.96875,"endTime":8300.0,"start":-2.3178860000000001,"startTime":8282.0},{"easing":9,"end":0.0,"endTime":8320.0,"start":1.96875,"startTime":8300.0},{"easing":0,"end":0.0,"endTime":8832.0,"start":0.0,"startTime":8320.0},{"easing":6,"end":5.0,"endTime":8896.0,"start":0.0,"startTime":8832.0},{"easing":6,"end":0.0,"endTime":8960.0,"start":5.0,"startTime":8896.0},{"easing":6,"end":5.0,"endTime":9024.0,"start":0.0,"startTime":8960.0},{"easing":6,"end":0.0,"endTime":9088.0,"start":5.0,"startTime":9024.0},{"easing":6,"end":-5.0,"endTime":9152.0,"start":0.0,"startTime":9088.0},{"easing":6,"end":0.0,"endTime":9216.0,"start":-5.0,"startTime":9152.0},{"easing":6,"end":-5.0,"endTime":9280.0,"start":0.0,"startTime":9216.0},{"easing":6,"end":0.0,"endTime":9344.0,"start":-5.0,"startTime":9280.0},{"easing":0,"end":0.0,"endTime":9984.0,"start":0.0,"startTime":9344.0},{"easing":6,"end":5.0,"endTime":10016.0,"start":0.0,"startTime":9984.0},{"easing":6,"end":0.0,"endTime":10048.0,"start":5.0,"startTime":10016.0},{"easing":6,"end":-5.0,"endTime":10080.0,"start":0.0,"startTime":10048.0},{"easing":6,"end":0.0,"endTime":10112.0,"start":-5.0,"startTime":10080.0},{"easing":30,"end":4.5811763000000001,"endTime":10158.0,"start":0.0,"startTime":10112.0},{"easing":0,"end":4.375,"endTime":10160.0,"start":4.5811763000000001,"startTime":10158.0},{"easing":0,"end":3.9531906000000001,"endTime":10163.0,"start":4.375,"startTime":10160.0},{"easing":0,"end":3.3750513,"endTime":10166.0,"start":3.9531906000000001,"startTime":10163.0},{"easing":0,"end":2.3178860000000001,"endTime":10170.0,"start":3.3750513,"startTime":10166.0},{"easing":18,"end":-4.921875,"endTime":10200.0,"start":2.3178860000000001,"startTime":10170.0},{"easing":9,"end":0.0,"endTime":10240.0,"start":-4.921875,"startTime":10200.0},{"easing":0,"end":0.0,"endTime":10304.0,"start":0.0,"startTime":10240.0},{"easing":6,"end":180.0,"endTime":10368.0,"start":0.0,"startTime":10304.0},{"easing":0,"end":180.0,"endTime":1000000000.0,"start":180.0,"startTime":10368.0}],"notesAbove":[{"floorPosition":5.4683539999999997,"holdTime":32.0,"positionX":-5.0,"speed":1.8,"time":256,"type":3},{"floorPosition":5.8101263000000003,"holdTime":0.0,"positionX":0.0,"speed":1.0,"time":272,"type":1},{"floorPosition":6.1518984000000003,"holdTime":0.0,"positionX":3.0,"speed":1.0,"time":288,"type":1},{"floorPosition":6.8354429999999997,"holdTime":32.0,"positionX":5.0,"speed":1.8,"time":320,"type":3},{"floorPosition":7.1772150000000003,"holdTime":0.0,"positionX":0.0,"speed":1.0,"time":336,"type":1},{"floorPosition":7.5189870000000001,"holdTime":0.0,"positionX":-3.0,"speed":1.0,"time":352,"type":1},{"floorPosition":8.2025319999999997,"holdTime":0.0,"positionX":-6.0,"speed":1.0,"time":384,"type":1},{"floorPosition":8.5443040000000003,"holdTime":0.0,"positionX":-3.0,"speed":1.0,"time":400,"type":1},{"floorPosition":8.8860759999999992,"holdTime":0.0,"positionX":0.0,"speed":1.0,"time":416,"type":1},{"floorPosition":9.2278479999999998,"holdTime":0.0,"positionX":3.0,"speed":1.0,"time":432,"type":1},{"floorPosition":9.5696200000000005,"holdTime":0.0,"positionX":6.0,"speed":1.0,"time":448,"type":1},{"floorPosition":10.253164,"holdTime":0.0,"positionX":0.0,"speed":1.0,"time":480,"type":4},{"floorPosition":10.936707999999999,"holdTime":0.0,"positionX":-4.0,"speed":1.0,"time":512,"type":1},{"floorPosition":11.278480999999999,"holdTime":0.0,"positionX":0.0,"speed":1.0,"time":528,"type":1},{"floorPosition":11.620253,"holdTime":0.0,"positionX":-4.0,"speed":1.0,"time":544,"type":1},{"floorPosition":11.962025000000001,"holdTime":0.0,"positionX":4.0,"speed":1.0,"time":560,"type":1},{"floorPosition":12.303796999999999,"holdTime":0.0,"positionX":0.0,"speed":1.0,"time":576,"type":1},{"floorPosition":12.645569,"holdTime":0.0,"positionX":4.0,"speed":1.0,"time":592,"type":1},{"floorPosition":12.987342,"holdTime":0.0,"positionX":-4.0,"speed":1.0,"time":608,"type":1},{"floorPosition":13.329114000000001,"holdTime":0.0,"positionX":4.0,"speed":1.0,"time":624,"type":1},{"floorPosition":13.670885999999999,"holdTime":0.0,"positionX":-4.0,"speed":1.0,"time":640,"type":1},{"floorPosition":14.012658,"holdTime":0.0,"positionX":-4.0,"speed":1.0,"time":656,"type":1},{"floorPosition":14.354430000000001,"holdTime":0.0,"positionX":0.0,"speed":1.0,"time":672,"type":1},{"floorPosition":14.696202,"holdTime":0.0,"positionX":0.0,"speed":1.0,"time":688,"type":1},{"floorPosition":15.037974,"holdTime":0.0,"positionX":4.0,"speed":1.0,"time":704,"type":1},{"floorPosition":15.379746000000001,"holdTime":0.0,"positionX":4.0,"speed":1.0,"time":720,"type":1},{"floorPosition":15.7215185,"holdTime":0.0,"positionX":0.0,"speed":1.0,"time":736,"type":1},{"floorPosition":16.063292000000001,"holdTime":0.0,"positionX":0.0,"speed":1.0,"time":752,"type":1},{"floorPosition":16.405063999999999,"holdTime":0.0,"positionX":-4.0,"speed":1.0,"time":768,"type":1},{"floorPosition":16.575949000000001,"holdTime":0.0,"positionX":0.0,"speed":1.0,"time":776,"type":1},{"floorPosition":16.746835999999998,"holdTime":0.0,"positionX":-4.0,"speed":1.0,"time":784,"type":1},{"floorPosition":17.088608000000001,"holdTime":0.0,"positionX":0.0,"speed":1.0,"time":800,"type":1},{"floorPosition":17.259492999999999,"holdTime":0.0,"positionX":-4.0,"speed":1.0,"time":808,"type":1},{"floorPosition":17.43038,"holdTime":0.0,"positionX":0.0,"speed":1.0,"time":816,"type":1},{"floorPosition":17.772151999999998,"holdTime":0.0,"positionX":0.0,"speed":1.0,"time":832,"type":1},{"floorPosition":17.943037,"holdTime":0.0,"positionX":4.0,"speed":1.0,"time":840,"type":1},{"floorPosition":18.113924000000001,"holdTime":0.0,"positionX":0.0,"speed":1.0,"time":848,"type":1},{"floorPosition":18.455696,"holdTime":0.0,"positionX":4.0,"speed":1.0,"time":864,"type":4},{"floorPosition":19.139240000000001,"holdTime":0.0,"positionX":-5.0,"speed":1.0,"time":896,"type":1},{"floorPosition":19.310124999999999,"holdTime":0.0,"positionX":-2.0,"speed":1.0,"time":904,"type":1},{"floorPosition":19.651897000000002,"holdTime":0.0,"positionX":-5.0,"speed":1.0,"time":920,"type":1},{"floorPosition":19.822783999999999,"holdTime":16.0,"positionX":-2.0,"speed":1.8,"time":928,"type":3},{"floorPosition":20.506329000000001,"holdTime":0.0,"positionX":-5.0,"speed":1.0,"time":960,"type":1},{"floorPosition":20.677216000000001,"holdTime":0.0,"positionX":0.0,"speed":1.0,"time":968,"type":1},{"floorPosition":21.018988,"holdTime":0.0,"positionX":-5.0,"speed":1.0,"time":984,"type":1},{"floorPosition":21.189872999999999,"holdTime":16.0,"positionX":0.0,"speed":1.8,"time":992,"type":3},{"floorPosition":21.873417,"holdTime":0.0,"positionX":-5.0,"speed":1.0,"time":1024,"type":1},{"floorPosition":22.044304,"holdTime":0.0,"positionX":2.0,"speed":1.0,"time":1032,"type":1},{"floorPosition":22.386075999999999,"holdTime":0.0,"positionX":-5.0,"speed":1.0,"time":1048,"type":1},{"floorPosition":22.556961000000001,"holdTime":16.0,"positionX":2.0,"speed":1.8,"time":1056,"type":3},{"floorPosition":23.240504999999999,"holdTime":0.0,"positionX":-5.0,"speed":1.0,"time":1088,"type":4},{"floorPosition":23.753164000000002,"holdTime":0.0,"positionX":5.0,"speed":1.0,"time":1112,"type":4},{"floorPosition":24.265820999999999,"holdTime":0.0,"positionX":0.0,"speed":1.0,"time":1136,"type":4},{"floorPosition":24.607593999999999,"holdTime":0.0,"positionX":5.0,"speed":1.0,"time":1152,"type":1},{"floorPosition":24.778479999999998,"holdTime":0.0,"positionX":2.0,"speed":1.0,"time":1160,"type":1},{"floorPosition":25.120253000000002,"holdTime":0.0,"positionX":5.0,"speed":1.0,"time":1176,"type":1},{"floorPosition":25.291138,"holdTime":16.0,"positionX":2.0,"speed":1.8,"time":1184,"type":3},{"floorPosition":25.974684,"holdTime":0.0,"positionX":5.0,"speed":1.0,"time":1216,"type":1},{"floorPosition":26.145568999999998,"holdTime":0.0,"positionX":0.0,"speed":1.0,"time":1224,"type":1},{"floorPosition":26.48734,"holdTime":0.0,"positionX":5.0,"speed":1.0,"time":1240,"type":1},{"floorPosition":26.658228000000001,"holdTime":16.0,"positionX":0.0,"speed":1.8,"time":1248,"type":3},{"floorPosition":27.341771999999999,"holdTime":0.0,"positionX":5.0,"speed":1.0,"time":1280,"type":1},{"floorPosition":27.512657000000001,"holdTime":0.0,"positionX":-2.0,"speed":1.0,"time":1288,"type":1},{"floorPosition":27.854430000000001,"holdTime":0.0,"positionX":5.0,"speed":1.0,"time":1304,"type":1},{"floorPosition":28.025316,"holdTime":16.0,"positionX":-2.0,"speed":1.8,"time":1312,"type":3},{"floorPosition":28.708860000000001,"holdTime":0.0,"positionX":5.0,"speed":1.0,"time":1344,"type":4},{"floorPosition":29.221518,"holdTime":0.0,"positionX":-5.0,"speed":1.0,"time":1368,"type":4},{"floorPosition":29.734176999999999,"holdTime":0.0,"positionX":0.0,"speed":1.0,"time":1392,"type":4},{"floorPosition":30.075949000000001,"holdTime":0.0,"positionX":-5.0,"speed":1.0,"time":1408,"type":1},{"floorPosition":30.246834,"holdTime":0.0,"positionX":-1.0,"speed":1.0,"time":1416,"type":1},{"floorPosition":30.588605999999999,"holdTime":0.0,"positionX":-3.0,"speed":1.0,"time":1432,"type":1},{"floorPosition":31.101265000000001,"holdTime":0.0,"positionX":-3.0,"speed":1.0,"time":1456,"type":1},{"floorPosition":31.443037,"holdTime":0.0,"positionX":-5.0,"speed":1.0,"time":1472,"type":1},{"floorPosition":31.443037,"holdTime":0.0,"positionX":0.0,"speed":1.0,"time":1472,"type":1},{"floorPosition":31.955696,"holdTime":0.0,"positionX":-2.0,"speed":1.0,"time":1496,"type":1},{"floorPosition":32.468353,"holdTime":0.0,"positionX":-2.0,"speed":1.0,"time":1520,"type":1},{"floorPosition":32.810127000000001,"holdTime":0.0,"positionX":-5.0,"speed":1.0,"time":1536,"type":1},{"floorPosition":32.981009999999998,"holdTime":0.0,"positionX":1.0,"speed":1.0,"time":1544,"type":1},{"floorPosition":33.322783999999999,"holdTime":0.0,"positionX":-1.0,"speed":1.0,"time":1560,"type":1},{"floorPosition":33.835439999999998,"holdTime":0.0,"positionX":-1.0,"speed":1.0,"time":1584,"type":1},{"floorPosition":34.177216000000001,"holdTime":0.0,"positionX":-5.0,"speed":1.0,"time":1600,"type":1},{"floorPosition":34.348100000000002,"holdTime":0.0,"positionX":2.0,"speed":1.0,"time":1608,"type":1},{"floorPosition":34.689872999999999,"holdTime":0.0,"positionX":0.0,"speed":1.0,"time":1624,"type":1},{"floorPosition":35.202530000000003,"holdTime":0.0,"positionX":0.0,"speed":1.0,"time":1648,"type":1},{"floorPosition":35.544303999999997,"holdTime":0.0,"positionX":5.0,"speed":1.0,"time":1664,"type":1},{"floorPosition":35.715187,"holdTime":0.0,"positionX":-2.0,"speed":1.0,"time":1672,"type":1},{"floorPosition":36.056959999999997,"holdTime":0.0,"positionX":0.0,"speed":1.0,"time":1688,"type":1},{"floorPosition":36.56962,"holdTime":0.0,"positionX":0.0,"speed":1.0,"time":1712,"type":1},{"floorPosition":36.911391999999999,"holdTime":0.0,"positionX":5.0,"speed":1.0,"time":1728,"type":1},{"floorPosition":37.082279999999997,"holdTime":0.0,"positionX":0.0,"speed":1.0,"time":1736,"type":1},{"floorPosition":37.424050000000001,"holdTime":0.0,"positionX":2.0,"speed":1.0,"time":1752,"type":1},{"floorPosition":37.936706999999998,"holdTime":0.0,"positionX":2.0,"speed":1.0,"time":1776,"type":1},{"floorPosition":38.278480000000002,"holdTime":0.0,"positionX":5.0,"speed":1.0,"time":1792,"type":1},{"floorPosition":38.449368,"holdTime":0.0,"positionX":1.0,"speed":1.0,"time":1800,"type":1},{"floorPosition":38.791137999999997,"holdTime":0.0,"positionX":3.0,"speed":1.0,"time":1816,"type":1},{"floorPosition":39.303795000000001,"holdTime":0.0,"positionX":3.0,"speed":1.0,"time":1840,"type":1},{"floorPosition":39.645569999999999,"holdTime":0.0,"positionX":5.0,"speed":1.0,"time":1856,"type":4},{"floorPosition":40.158225999999999,"holdTime":0.0,"positionX":0.0,"speed":1.0,"time":1880,"type":4},{"floorPosition":40.670883000000003,"holdTime":0.0,"positionX":-5.0,"speed":1.0,"time":1904,"type":4},{"floorPosition":41.012656999999997,"holdTime":96.0,"positionX":4.0,"speed":1.8,"time":1920,"type":3},{"floorPosition":41.696199999999997,"holdTime":0.0,"positionX":-4.0,"speed":1.0,"time":1952,"type":4},{"floorPosition":42.379745,"holdTime":0.0,"positionX":0.0,"speed":1.0,"time":1984,"type":1},{"floorPosition":43.063290000000002,"holdTime":0.0,"positionX":-3.0,"speed":1.0,"time":2016,"type":4},{"floorPosition":43.746834,"holdTime":96.0,"positionX":-4.0,"speed":1.8,"time":2048,"type":3},{"floorPosition":44.430377999999997,"holdTime":0.0,"positionX":4.0,"speed":1.0,"time":2080,"type":4},{"floorPosition":45.113922000000002,"holdTime":0.0,"positionX":0.0,"speed":1.0,"time":2112,"type":1},{"floorPosition":45.797466,"holdTime":0.0,"positionX":3.0,"speed":1.0,"time":2144,"type":4},{"floorPosition":46.481009999999998,"holdTime":32.0,"positionX":4.0,"speed":1.8,"time":2176,"type":3},{"floorPosition":47.164555,"holdTime":0.0,"positionX":0.0,"speed":1.0,"time":2208,"type":4},{"floorPosition":47.848100000000002,"holdTime":32.0,"positionX":-4.0,"speed":1.8,"time":2240,"type":3},{"floorPosition":48.531643000000003,"holdTime":0.0,"positionX":0.0,"speed":1.0,"time":2272,"type":4},{"floorPosition":49.215187,"holdTime":32.0,"positionX":5.0,"speed":1.8,"time":2304,"type":3},{"floorPosition":49.89873,"holdTime":32.0,"positionX":-2.0,"speed":1.8,"time":2336,"type":3},{"floorPosition":50.582275000000003,"holdTime":32.0,"positionX":3.0,"speed":1.8,"time":2368,"type":3},{"floorPosition":51.265819999999998,"holdTime":32.0,"positionX":-5.0,"speed":1.8,"time":2400,"type":3},{"floorPosition":51.949368,"holdTime":0.0,"positionX":4.0,"speed":1.0,"time":2432,"type":1},{"floorPosition":52.632910000000003,"holdTime":0.0,"positionX":4.0,"speed":1.0,"time":2464,"type":4},{"floorPosition":53.316456000000002,"holdTime":0.0,"positionX":1.0,"speed":1.0,"time":2496,"type":1},{"floorPosition":54.0,"holdTime":0.0,"positionX":1.0,"speed":1.0,"time":2528,"type":4},{"floorPosition":54.683543999999998,"holdTime":0.0,"positionX":-4.0,"speed":1.0,"time":2560,"type":1},{"floorPosition":55.367089999999997,"holdTime":0.0,"positionX":-4.0,"speed":1.0,"time":2592,"type":4},{"floorPosition":56.050632,"holdTime":0.0,"positionX":-1.0,"speed":1.0,"time":2624,"type":1},{"floorPosition":56.734177000000003,"holdTime":0.0,"positionX":-1.0,"speed":1.0,"time":2656,"type":4},{"floorPosition":57.417720000000003,"holdTime":0.0,"positionX":-4.0,"speed":1.0,"time":2688,"type":1},{"floorPosition":57.75949,"holdTime":0.0,"positionX":-4.0,"speed":1.0,"time":2704,"type":1},{"floorPosition":58.101264999999998,"holdTime":0.0,"positionX":4.0,"speed":1.0,"time":2720,"type":1},{"floorPosition":58.443035000000002,"holdTime":0.0,"positionX":4.0,"speed":1.0,"time":2736,"type":1},{"floorPosition":58.78481,"holdTime":0.0,"positionX":-2.0,"speed":1.0,"time":2752,"type":1},{"floorPosition":59.126579999999997,"holdTime":0.0,"positionX":-2.0,"speed":1.0,"time":2768,"type":1},{"floorPosition":59.468353,"holdTime":0.0,"positionX":2.0,"speed":1.0,"time":2784,"type":1},{"floorPosition":59.810122999999997,"holdTime":0.0,"positionX":2.0,"speed":1.0,"time":2800,"type":1},{"floorPosition":60.151896999999998,"holdTime":0.0,"positionX":-4.0,"speed":1.0,"time":2816,"type":1},{"floorPosition":60.322783999999999,"holdTime":0.0,"positionX":0.0,"speed":1.0,"time":2824,"type":1},{"floorPosition":60.493668,"holdTime":0.0,"positionX":-2.0,"speed":1.0,"time":2832,"type":1},{"floorPosition":60.835439999999998,"holdTime":0.0,"positionX":4.0,"speed":1.0,"time":2848,"type":1},{"floorPosition":61.006329999999998,"holdTime":0.0,"positionX":0.0,"speed":1.0,"time":2856,"type":1},{"floorPosition":61.177210000000002,"holdTime":0.0,"positionX":2.0,"speed":1.0,"time":2864,"type":1},{"floorPosition":61.518985999999998,"holdTime":0.0,"positionX":-3.0,"speed":1.0,"time":2880,"type":4},{"floorPosition":61.860759999999999,"holdTime":0.0,"positionX":3.0,"speed":1.0,"time":2896,"type":4},{"floorPosition":62.202530000000003,"holdTime":0.0,"positionX":-3.0,"speed":1.0,"time":2912,"type":4},{"floorPosition":62.544303999999997,"holdTime":0.0,"positionX":3.0,"speed":1.0,"time":2928,"type":4},{"floorPosition":62.886074000000001,"holdTime":0.0,"positionX":-5.0,"speed":1.0,"time":2944,"type":1},{"floorPosition":63.227848000000002,"holdTime":0.0,"positionX":-1.0,"speed":1.0,"time":2960,"type":1},{"floorPosition":63.56962,"holdTime":0.0,"positionX":-3.0,"speed":1.0,"time":2976,"type":1},{"floorPosition":63.911391999999999,"holdTime":0.0,"positionX":1.0,"speed":1.0,"time":2992,"type":1},{"floorPosition":64.253169999999997,"holdTime":0.0,"positionX":-1.0,"speed":1.0,"time":3008,"type":1},{"floorPosition":64.594930000000005,"holdTime":0.0,"positionX":3.0,"speed":1.0,"time":3024,"type":2},{"floorPosition":64.765820000000005,"holdTime":0.0,"positionX":2.0,"speed":1.0,"time":3032,"type":2},{"floorPosition":64.936710000000005,"holdTime":0.0,"positionX":1.0,"speed":1.0,"time":3040,"type":2},{"floorPosition":65.620255,"holdTime":0.0,"positionX":5.0,"speed":1.0,"time":3072,"type":1},{"floorPosition":65.962019999999995,"holdTime":0.0,"positionX":1.0,"speed":1.0,"time":3088,"type":1},{"floorPosition":66.303794999999994,"holdTime":0.0,"positionX":3.0,"speed":1.0,"time":3104,"type":1},{"floorPosition":66.645570000000006,"holdTime":0.0,"positionX":-1.0,"speed":1.0,"time":3120,"type":1},{"floorPosition":66.987340000000003,"holdTime":0.0,"positionX":1.0,"speed":1.0,"time":3136,"type":2},{"floorPosition":67.158225999999999,"holdTime":0.0,"positionX":2.0,"speed":1.0,"time":3144,"type":2},{"floorPosition":67.32911,"holdTime":0.0,"positionX":3.0,"speed":1.0,"time":3152,"type":2},{"floorPosition":67.670879999999997,"holdTime":0.0,"positionX":-4.0,"speed":1.0,"time":3168,"type":1},{"floorPosition":67.670879999999997,"holdTime":0.0,"positionX":4.0,"speed":1.0,"time":3168,"type":1},{"floorPosition":68.354429999999994,"holdTime":0.0,"positionX":-5.0,"speed":1.0,"time":3200,"type":1},{"floorPosition":68.696200000000005,"holdTime":0.0,"positionX":-1.0,"speed":1.0,"time":3216,"type":1},{"floorPosition":69.037970000000001,"holdTime":0.0,"positionX":-3.0,"speed":1.0,"time":3232,"type":1},{"floorPosition":69.379745,"holdTime":0.0,"positionX":1.0,"speed":1.0,"time":3248,"type":1},{"floorPosition":69.721519999999998,"holdTime":0.0,"positionX":-1.0,"speed":1.0,"time":3264,"type":1},{"floorPosition":70.063286000000005,"holdTime":0.0,"positionX":3.0,"speed":1.0,"time":3280,"type":2},{"floorPosition":70.234179999999995,"holdTime":0.0,"positionX":2.0,"speed":1.0,"time":3288,"type":2},{"floorPosition":70.405060000000006,"holdTime":0.0,"positionX":1.0,"speed":1.0,"time":3296,"type":2},{"floorPosition":71.088610000000003,"holdTime":0.0,"positionX":5.0,"speed":1.0,"time":3328,"type":1},{"floorPosition":71.430374,"holdTime":0.0,"positionX":1.0,"speed":1.0,"time":3344,"type":1},{"floorPosition":71.772149999999996,"holdTime":0.0,"positionX":3.0,"speed":1.0,"time":3360,"type":1},{"floorPosition":72.113919999999993,"holdTime":0.0,"positionX":-1.0,"speed":1.0,"time":3376,"type":1},{"floorPosition":72.455696000000003,"holdTime":0.0,"positionX":1.0,"speed":1.0,"time":3392,"type":2},{"floorPosition":72.626580000000004,"holdTime":0.0,"positionX":2.0,"speed":1.0,"time":3400,"type":2},{"floorPosition":72.797470000000004,"holdTime":0.0,"positionX":3.0,"speed":1.0,"time":3408,"type":2},{"floorPosition":73.139240000000001,"holdTime":0.0,"positionX":-4.0,"speed":1.0,"time":3424,"type":1},{"floorPosition":73.139240000000001,"holdTime":0.0,"positionX":4.0,"speed":1.0,"time":3424,"type":1},{"floorPosition":73.822783999999999,"holdTime":0.0,"positionX":-5.0,"speed":1.0,"time":3456,"type":1},{"floorPosition":74.164559999999994,"holdTime":0.0,"positionX":0.0,"speed":1.0,"time":3472,"type":1},{"floorPosition":74.506325000000004,"holdTime":0.0,"positionX":-4.0,"speed":1.0,"time":3488,"type":1},{"floorPosition":74.848100000000002,"holdTime":0.0,"positionX":-2.0,"speed":1.0,"time":3504,"type":1},{"floorPosition":75.189869999999999,"holdTime":0.0,"positionX":-5.0,"speed":1.0,"time":3520,"type":1},{"floorPosition":75.531649999999999,"holdTime":0.0,"positionX":0.0,"speed":1.0,"time":3536,"type":2},{"floorPosition":75.702529999999996,"holdTime":0.0,"positionX":1.0,"speed":1.0,"time":3544,"type":2},{"floorPosition":75.873410000000007,"holdTime":0.0,"positionX":2.0,"speed":1.0,"time":3552,"type":2},{"floorPosition":76.215190000000007,"holdTime":0.0,"positionX":-3.0,"speed":1.0,"time":3568,"type":4},{"floorPosition":76.556960000000004,"holdTime":0.0,"positionX":5.0,"speed":1.0,"time":3584,"type":1},{"floorPosition":76.898735000000002,"holdTime":0.0,"positionX":0.0,"speed":1.0,"time":3600,"type":1},{"floorPosition":77.240499999999997,"holdTime":0.0,"positionX":4.0,"speed":1.0,"time":3616,"type":1},{"floorPosition":77.582274999999996,"holdTime":0.0,"positionX":2.0,"speed":1.0,"time":3632,"type":1},{"floorPosition":77.924049999999994,"holdTime":0.0,"positionX":4.0,"speed":1.0,"time":3648,"type":2},{"floorPosition":78.094930000000005,"holdTime":0.0,"positionX":3.0,"speed":1.0,"time":3656,"type":2},{"floorPosition":78.265820000000005,"holdTime":0.0,"positionX":2.0,"speed":1.0,"time":3664,"type":2},{"floorPosition":78.607590000000002,"holdTime":0.0,"positionX":-4.0,"speed":1.0,"time":3680,"type":2},{"floorPosition":78.778480000000002,"holdTime":0.0,"positionX":-3.0,"speed":1.0,"time":3688,"type":2},{"floorPosition":78.949359999999999,"holdTime":0.0,"positionX":-2.0,"speed":1.0,"time":3696,"type":2},{"floorPosition":79.291139999999999,"holdTime":0.0,"positionX":-5.0,"speed":1.0,"time":3712,"type":1},{"floorPosition":79.632909999999995,"holdTime":0.0,"positionX":0.0,"speed":1.0,"time":3728,"type":1},{"floorPosition":79.974680000000006,"holdTime":0.0,"positionX":-4.0,"speed":1.0,"time":3744,"type":1},{"floorPosition":80.316450000000003,"holdTime":0.0,"positionX":-2.0,"speed":1.0,"time":3760,"type":1},{"floorPosition":80.658225999999999,"holdTime":0.0,"positionX":-5.0,"speed":1.0,"time":3776,"type":1},{"floorPosition":81.0,"holdTime":0.0,"positionX":0.0,"speed":1.0,"time":3792,"type":2},{"floorPosition":81.170879999999997,"holdTime":0.0,"positionX":1.0,"speed":1.0,"time":3800,"type":2},{"floorPosition":81.341769999999997,"holdTime":0.0,"positionX":2.0,"speed":1.0,"time":3808,"type":2},{"floorPosition":81.683539999999994,"holdTime":0.0,"positionX":-3.0,"speed":1.0,"time":3824,"type":4},{"floorPosition":82.025313999999995,"holdTime":0.0,"positionX":5.0,"speed":1.0,"time":3840,"type":1},{"floorPosition":82.367090000000005,"holdTime":0.0,"positionX":0.0,"speed":1.0,"time":3856,"type":1},{"floorPosition":82.708860000000001,"holdTime":0.0,"positionX":4.0,"speed":1.0,"time":3872,"type":1},{"floorPosition":83.050629999999998,"holdTime":0.0,"positionX":2.0,"speed":1.0,"time":3888,"type":1},{"floorPosition":83.392399999999995,"holdTime":0.0,"positionX":4.0,"speed":1.0,"time":3904,"type":4},{"floorPosition":84.075950000000006,"holdTime":0.0,"positionX":-4.0,"speed":1.0,"time":3936,"type":4},{"floorPosition":84.75949,"holdTime":32.0,"positionX":0.0,"speed":1.8,"time":3968,"type":3},{"floorPosition":85.784805000000006,"holdTime":0.0,"positionX":0.0,"speed":1.0,"time":4016,"type":2},{"floorPosition":85.955696000000003,"holdTime":0.0,"positionX":0.0,"speed":1.0,"time":4024,"type":2},{"floorPosition":86.126580000000004,"holdTime":0.0,"positionX":0.0,"speed":1.0,"time":4032,"type":2},{"floorPosition":86.810130000000001,"holdTime":0.0,"positionX":0.0,"speed":1.0,"time":4064,"type":2},{"floorPosition":87.493669999999995,"holdTime":0.0,"positionX":0.0,"speed":1.0,"time":4096,"type":2},{"floorPosition":88.177216000000001,"holdTime":0.0,"positionX":0.0,"speed":1.0,"time":4128,"type":2},{"floorPosition":88.860755999999995,"holdTime":0.0,"positionX":0.0,"speed":1.0,"time":4160,"type":2},{"floorPosition":89.544303999999997,"holdTime":0.0,"positionX":0.0,"speed":1.0,"time":4192,"type":2},{"floorPosition":90.227844000000005,"holdTime":96.0,"positionX":0.0,"speed":1.8,"time":4224,"type":3},{"floorPosition":95.012659999999997,"holdTime":0.0,"positionX":0.0,"speed":1.0,"time":4448,"type":4},{"floorPosition":95.696200000000005,"holdTime":0.0,"positionX":-1.0,"speed":1.0,"time":4480,"type":1},{"floorPosition":95.696200000000005,"holdTime":0.0,"positionX":-5.0,"speed":1.0,"time":4480,"type":1},{"floorPosition":96.379745,"holdTime":0.0,"positionX":-3.0,"speed":1.0,"time":4512,"type":4},{"floorPosition":97.063286000000005,"holdTime":0.0,"positionX":5.0,"speed":1.0,"time":4544,"type":1},{"floorPosition":97.063286000000005,"holdTime":0.0,"positionX":1.0,"speed":1.0,"time":4544,"type":1},{"floorPosition":97.746830000000003,"holdTime":0.0,"positionX":3.0,"speed":1.0,"time":4576,"type":4},{"floorPosition":98.430374,"holdTime":0.0,"positionX":1.0,"speed":1.0,"time":4608,"type":1},{"floorPosition":98.430374,"holdTime":0.0,"positionX":-5.0,"speed":1.0,"time":4608,"type":1},{"floorPosition":99.113919999999993,"holdTime":0.0,"positionX":-2.0,"speed":1.0,"time":4640,"type":4},{"floorPosition":99.797460000000001,"holdTime":0.0,"positionX":5.0,"speed":1.0,"time":4672,"type":1},{"floorPosition":99.797460000000001,"holdTime":0.0,"positionX":-1.0,"speed":1.0,"time":4672,"type":1},{"floorPosition":100.48101,"holdTime":0.0,"positionX":2.0,"speed":1.0,"time":4704,"type":4},{"floorPosition":101.16455000000001,"holdTime":0.0,"positionX":-5.0,"speed":1.0,"time":4736,"type":1},{"floorPosition":101.506325,"holdTime":0.0,"positionX":-5.0,"speed":1.0,"time":4752,"type":1},{"floorPosition":101.8481,"holdTime":0.0,"positionX":-2.0,"speed":1.0,"time":4768,"type":1},{"floorPosition":102.18987,"holdTime":0.0,"positionX":-2.0,"speed":1.0,"time":4784,"type":1},{"floorPosition":102.53164,"holdTime":0.0,"positionX":2.0,"speed":1.0,"time":4800,"type":1},{"floorPosition":102.87341000000001,"holdTime":0.0,"positionX":2.0,"speed":1.0,"time":4816,"type":1},{"floorPosition":103.21519000000001,"holdTime":0.0,"positionX":5.0,"speed":1.0,"time":4832,"type":1},{"floorPosition":103.55696,"holdTime":0.0,"positionX":5.0,"speed":1.0,"time":4848,"type":1},{"floorPosition":103.898735,"holdTime":0.0,"positionX":4.0,"speed":1.0,"time":4864,"type":2},{"floorPosition":104.06962,"holdTime":0.0,"positionX":3.0,"speed":1.0,"time":4872,"type":2},{"floorPosition":104.2405,"holdTime":0.0,"positionX":2.0,"speed":1.0,"time":4880,"type":2},{"floorPosition":104.41139,"holdTime":0.0,"positionX":1.0,"speed":1.0,"time":4888,"type":2},{"floorPosition":104.582275,"holdTime":0.0,"positionX":0.0,"speed":1.0,"time":4896,"type":2},{"floorPosition":104.75315999999999,"holdTime":0.0,"positionX":-1.0,"speed":1.0,"time":4904,"type":2},{"floorPosition":104.92404999999999,"holdTime":0.0,"positionX":-2.0,"speed":1.0,"time":4912,"type":2},{"floorPosition":105.09493000000001,"holdTime":0.0,"positionX":-3.0,"speed":1.0,"time":4920,"type":2},{"floorPosition":105.26582000000001,"holdTime":0.0,"positionX":-4.0,"speed":1.0,"time":4928,"type":2},{"floorPosition":105.351265,"holdTime":0.0,"positionX":-3.0,"speed":1.0,"time":4932,"type":2},{"floorPosition":105.43671000000001,"holdTime":0.0,"positionX":-2.0,"speed":1.0,"time":4936,"type":2},{"floorPosition":105.52215,"holdTime":0.0,"positionX":-1.0,"speed":1.0,"time":4940,"type":2},{"floorPosition":105.60759,"holdTime":0.0,"positionX":0.0,"speed":1.0,"time":4944,"type":2},{"floorPosition":105.69304,"holdTime":0.0,"positionX":1.0,"speed":1.0,"time":4948,"type":2},{"floorPosition":105.77848,"holdTime":0.0,"positionX":2.0,"speed":1.0,"time":4952,"type":2},{"floorPosition":105.86391999999999,"holdTime":0.0,"positionX":3.0,"speed":1.0,"time":4956,"type":2},{"floorPosition":105.94936,"holdTime":0.0,"positionX":4.0,"speed":1.0,"time":4960,"type":2},{"floorPosition":106.63291,"holdTime":0.0,"positionX":0.0,"speed":1.0,"time":4992,"type":1},{"floorPosition":106.80379499999999,"holdTime":0.0,"positionX":0.0,"speed":1.0,"time":5000,"type":2},{"floorPosition":106.97468000000001,"holdTime":0.0,"positionX":0.0,"speed":1.0,"time":5008,"type":2},{"floorPosition":107.14557000000001,"holdTime":0.0,"positionX":0.0,"speed":1.0,"time":5016,"type":2},{"floorPosition":107.31645,"holdTime":0.0,"positionX":0.0,"speed":1.0,"time":5024,"type":2},{"floorPosition":107.487335,"holdTime":0.0,"positionX":0.0,"speed":1.0,"time":5032,"type":2},{"floorPosition":107.658226,"holdTime":0.0,"positionX":0.0,"speed":1.0,"time":5040,"type":2},{"floorPosition":107.82911,"holdTime":0.0,"positionX":0.0,"speed":1.0,"time":5048,"type":2},{"floorPosition":108.0,"holdTime":0.0,"positionX":0.0,"speed":1.0,"time":5056,"type":2},{"floorPosition":108.17088,"holdTime":0.0,"positionX":0.0,"speed":1.0,"time":5064,"type":2},{"floorPosition":108.34177,"holdTime":0.0,"positionX":0.0,"speed":1.0,"time":5072,"type":2},{"floorPosition":108.51266,"holdTime":0.0,"positionX":0.0,"speed":1.0,"time":5080,"type":2},{"floorPosition":108.68353999999999,"holdTime":0.0,"positionX":0.0,"speed":1.0,"time":5088,"type":2},{"floorPosition":108.85442999999999,"holdTime":0.0,"positionX":0.0,"speed":1.0,"time":5096,"type":2},{"floorPosition":109.02531399999999,"holdTime":0.0,"positionX":0.0,"speed":1.0,"time":5104,"type":2},{"floorPosition":109.36709,"holdTime":0.0,"positionX":4.0,"speed":1.0,"time":5120,"type":2},{"floorPosition":109.45253,"holdTime":0.0,"positionX":3.0,"speed":1.0,"time":5124,"type":2},{"floorPosition":109.53797,"holdTime":0.0,"positionX":2.0,"speed":1.0,"time":5128,"type":2},{"floorPosition":109.62341000000001,"holdTime":0.0,"positionX":1.0,"speed":1.0,"time":5132,"type":2},{"floorPosition":109.708855,"holdTime":0.0,"positionX":0.0,"speed":1.0,"time":5136,"type":2},{"floorPosition":109.794304,"holdTime":0.0,"positionX":-1.0,"speed":1.0,"time":5140,"type":2},{"floorPosition":109.879745,"holdTime":0.0,"positionX":-2.0,"speed":1.0,"time":5144,"type":2},{"floorPosition":109.96519000000001,"holdTime":0.0,"positionX":-3.0,"speed":1.0,"time":5148,"type":2},{"floorPosition":110.05063,"holdTime":0.0,"positionX":-4.0,"speed":1.0,"time":5152,"type":2},{"floorPosition":110.05063,"holdTime":0.0,"positionX":4.0,"speed":1.0,"time":5152,"type":2},{"floorPosition":110.13607,"holdTime":0.0,"positionX":3.0,"speed":1.0,"time":5156,"type":2},{"floorPosition":110.22152,"holdTime":0.0,"positionX":2.0,"speed":1.0,"time":5160,"type":2},{"floorPosition":110.30696,"holdTime":0.0,"positionX":1.0,"speed":1.0,"time":5164,"type":2},{"floorPosition":110.39239999999999,"holdTime":0.0,"positionX":0.0,"speed":1.0,"time":5168,"type":2},{"floorPosition":110.477844,"holdTime":0.0,"positionX":-1.0,"speed":1.0,"time":5172,"type":2},{"floorPosition":110.56328600000001,"holdTime":0.0,"positionX":-2.0,"speed":1.0,"time":5176,"type":2},{"floorPosition":110.648735,"holdTime":0.0,"positionX":-3.0,"speed":1.0,"time":5180,"type":2},{"floorPosition":110.73417999999999,"holdTime":0.0,"positionX":-4.0,"speed":1.0,"time":5184,"type":2},{"floorPosition":111.41772,"holdTime":0.0,"positionX":0.0,"speed":1.0,"time":5216,"type":4},{"floorPosition":112.101265,"holdTime":0.0,"positionX":-5.0,"speed":1.0,"time":5248,"type":1},{"floorPosition":112.44302999999999,"holdTime":0.0,"positionX":0.0,"speed":1.0,"time":5264,"type":1},{"floorPosition":112.78480500000001,"holdTime":0.0,"positionX":-3.0,"speed":1.0,"time":5280,"type":1},{"floorPosition":113.12658,"holdTime":16.0,"positionX":3.0,"speed":1.8,"time":5296,"type":3},{"floorPosition":113.81013,"holdTime":0.0,"positionX":-5.0,"speed":1.0,"time":5328,"type":1},{"floorPosition":114.15188999999999,"holdTime":0.0,"positionX":-2.0,"speed":1.0,"time":5344,"type":1},{"floorPosition":114.49366999999999,"holdTime":0.0,"positionX":1.0,"speed":1.0,"time":5360,"type":1},{"floorPosition":114.83544000000001,"holdTime":0.0,"positionX":5.0,"speed":1.0,"time":5376,"type":1},{"floorPosition":115.177216,"holdTime":0.0,"positionX":0.0,"speed":1.0,"time":5392,"type":1},{"floorPosition":115.51898,"holdTime":0.0,"positionX":3.0,"speed":1.0,"time":5408,"type":1},{"floorPosition":115.86075599999999,"holdTime":16.0,"positionX":-3.0,"speed":1.8,"time":5424,"type":3},{"floorPosition":116.544304,"holdTime":0.0,"positionX":5.0,"speed":1.0,"time":5456,"type":1},{"floorPosition":116.88607,"holdTime":0.0,"positionX":2.0,"speed":1.0,"time":5472,"type":1},{"floorPosition":117.227844,"holdTime":0.0,"positionX":-1.0,"speed":1.0,"time":5488,"type":1},{"floorPosition":117.56962,"holdTime":0.0,"positionX":-4.0,"speed":1.0,"time":5504,"type":1},{"floorPosition":117.91139,"holdTime":0.0,"positionX":0.0,"speed":1.0,"time":5520,"type":1},{"floorPosition":118.25315999999999,"holdTime":0.0,"positionX":-3.0,"speed":1.0,"time":5536,"type":1},{"floorPosition":118.59493000000001,"holdTime":0.0,"positionX":1.0,"speed":1.0,"time":5552,"type":1},{"floorPosition":118.93671000000001,"holdTime":0.0,"positionX":-2.0,"speed":1.0,"time":5568,"type":1},{"floorPosition":119.27848,"holdTime":0.0,"positionX":2.0,"speed":1.0,"time":5584,"type":2},{"floorPosition":119.44936,"holdTime":0.0,"positionX":3.0,"speed":1.0,"time":5592,"type":2},{"floorPosition":119.62025,"holdTime":0.0,"positionX":4.0,"speed":1.0,"time":5600,"type":2},{"floorPosition":119.79114,"holdTime":0.0,"positionX":3.0,"speed":1.0,"time":5608,"type":2},{"floorPosition":119.96202,"holdTime":0.0,"positionX":2.0,"speed":1.0,"time":5616,"type":2},{"floorPosition":120.30379499999999,"holdTime":0.0,"positionX":-2.0,"speed":1.0,"time":5632,"type":1},{"floorPosition":120.64557000000001,"holdTime":0.0,"positionX":-2.0,"speed":1.0,"time":5648,"type":1},{"floorPosition":120.987335,"holdTime":0.0,"positionX":2.0,"speed":1.0,"time":5664,"type":1},{"floorPosition":121.32911,"holdTime":0.0,"positionX":2.0,"speed":1.0,"time":5680,"type":1},{"floorPosition":121.67088,"holdTime":16.0,"positionX":0.0,"speed":1.8,"time":5696,"type":3},{"floorPosition":122.35442,"holdTime":0.0,"positionX":0.0,"speed":1.0,"time":5728,"type":4},{"floorPosition":123.03797,"holdTime":64.0,"positionX":-4.0,"speed":1.8,"time":5760,"type":3},{"floorPosition":123.72152,"holdTime":0.0,"positionX":0.0,"speed":1.0,"time":5792,"type":4},{"floorPosition":124.06328600000001,"holdTime":0.0,"positionX":0.0,"speed":1.0,"time":5808,"type":4},{"floorPosition":124.40506000000001,"holdTime":64.0,"positionX":4.0,"speed":1.8,"time":5824,"type":3},{"floorPosition":125.08861,"holdTime":0.0,"positionX":0.0,"speed":1.0,"time":5856,"type":4},{"floorPosition":125.430374,"holdTime":0.0,"positionX":0.0,"speed":1.0,"time":5872,"type":4},{"floorPosition":125.77215,"holdTime":0.0,"positionX":-4.0,"speed":1.0,"time":5888,"type":1},{"floorPosition":126.11391999999999,"holdTime":0.0,"positionX":-4.0,"speed":1.0,"time":5904,"type":1},{"floorPosition":126.455696,"holdTime":0.0,"positionX":0.0,"speed":1.0,"time":5920,"type":1},{"floorPosition":126.79746,"holdTime":0.0,"positionX":0.0,"speed":1.0,"time":5936,"type":1},{"floorPosition":127.13924,"holdTime":0.0,"positionX":4.0,"speed":1.0,"time":5952,"type":1},{"floorPosition":127.822784,"holdTime":0.0,"positionX":-4.0,"speed":1.0,"time":5984,"type":4},{"floorPosition":127.822784,"holdTime":0.0,"positionX":4.0,"speed":1.0,"time":5984,"type":4},{"floorPosition":128.50632999999999,"holdTime":0.0,"positionX":-2.0,"speed":1.0,"time":6016,"type":1},{"floorPosition":128.84809999999999,"holdTime":0.0,"positionX":0.0,"speed":1.0,"time":6032,"type":1},{"floorPosition":129.18987000000001,"holdTime":0.0,"positionX":2.0,"speed":1.0,"time":6048,"type":1},{"floorPosition":129.53165000000001,"holdTime":0.0,"positionX":0.0,"speed":1.0,"time":6064,"type":1},{"floorPosition":129.87341000000001,"holdTime":0.0,"positionX":-3.0,"speed":1.0,"time":6080,"type":1},{"floorPosition":130.21518,"holdTime":0.0,"positionX":0.0,"speed":1.0,"time":6096,"type":1},{"floorPosition":130.55696,"holdTime":0.0,"positionX":3.0,"speed":1.0,"time":6112,"type":1},{"floorPosition":130.89873,"holdTime":0.0,"positionX":0.0,"speed":1.0,"time":6128,"type":1},{"floorPosition":131.24051,"holdTime":32.0,"positionX":-5.0,"speed":1.8,"time":6144,"type":3},{"floorPosition":131.92403999999999,"holdTime":0.0,"positionX":0.0,"speed":1.0,"time":6176,"type":4},{"floorPosition":132.60758999999999,"holdTime":32.0,"positionX":5.0,"speed":1.8,"time":6208,"type":3},{"floorPosition":133.29114000000001,"holdTime":0.0,"positionX":0.0,"speed":1.0,"time":6240,"type":4},{"floorPosition":133.97469000000001,"holdTime":0.0,"positionX":-3.0,"speed":1.0,"time":6272,"type":2},{"floorPosition":134.48733999999999,"holdTime":0.0,"positionX":-3.0,"speed":1.0,"time":6296,"type":2},{"floorPosition":135.0,"holdTime":0.0,"positionX":-3.0,"speed":1.0,"time":6320,"type":2},{"floorPosition":135.51265000000001,"holdTime":0.0,"positionX":-3.0,"speed":1.0,"time":6344,"type":2},{"floorPosition":136.02530999999999,"holdTime":0.0,"positionX":-3.0,"speed":1.0,"time":6368,"type":2},{"floorPosition":136.70885999999999,"holdTime":0.0,"positionX":-1.0,"speed":1.0,"time":6400,"type":2},{"floorPosition":137.22150999999999,"holdTime":0.0,"positionX":-1.0,"speed":1.0,"time":6424,"type":2},{"floorPosition":137.73418000000001,"holdTime":0.0,"positionX":-1.0,"speed":1.0,"time":6448,"type":2},{"floorPosition":138.24682999999999,"holdTime":0.0,"positionX":-1.0,"speed":1.0,"time":6472,"type":2},{"floorPosition":138.75949,"holdTime":0.0,"positionX":-1.0,"speed":1.0,"time":6496,"type":2},{"floorPosition":139.44304,"holdTime":0.0,"positionX":1.0,"speed":1.0,"time":6528,"type":2},{"floorPosition":139.95569,"holdTime":0.0,"positionX":1.0,"speed":1.0,"time":6552,"type":2},{"floorPosition":140.46834999999999,"holdTime":0.0,"positionX":1.0,"speed":1.0,"time":6576,"type":2},{"floorPosition":140.98099999999999,"holdTime":0.0,"positionX":1.0,"speed":1.0,"time":6600,"type":2},{"floorPosition":141.49367000000001,"holdTime":0.0,"positionX":1.0,"speed":1.0,"time":6624,"type":2},{"floorPosition":142.17722000000001,"holdTime":0.0,"positionX":3.0,"speed":1.0,"time":6656,"type":2},{"floorPosition":142.68987000000001,"holdTime":0.0,"positionX":3.0,"speed":1.0,"time":6680,"type":2},{"floorPosition":143.20253,"holdTime":0.0,"positionX":3.0,"speed":1.0,"time":6704,"type":2},{"floorPosition":143.71518,"holdTime":0.0,"positionX":3.0,"speed":1.0,"time":6728,"type":2},{"floorPosition":144.22783999999999,"holdTime":0.0,"positionX":3.0,"speed":1.0,"time":6752,"type":2},{"floorPosition":144.91139000000001,"holdTime":0.0,"positionX":-3.0,"speed":1.0,"time":6784,"type":2},{"floorPosition":145.42403999999999,"holdTime":0.0,"positionX":-3.0,"speed":1.0,"time":6808,"type":2},{"floorPosition":145.9367,"holdTime":0.0,"positionX":-3.0,"speed":1.0,"time":6832,"type":2},{"floorPosition":146.44936000000001,"holdTime":0.0,"positionX":-3.0,"speed":1.0,"time":6856,"type":2},{"floorPosition":146.96202,"holdTime":0.0,"positionX":-3.0,"speed":1.0,"time":6880,"type":2},{"floorPosition":147.64556999999999,"holdTime":0.0,"positionX":2.0,"speed":1.0,"time":6912,"type":2},{"floorPosition":148.15822,"holdTime":0.0,"positionX":2.0,"speed":1.0,"time":6936,"type":2},{"floorPosition":148.67088000000001,"holdTime":0.0,"positionX":2.0,"speed":1.0,"time":6960,"type":2},{"floorPosition":149.18355,"holdTime":0.0,"positionX":2.0,"speed":1.0,"time":6984,"type":2},{"floorPosition":149.6962,"holdTime":0.0,"positionX":2.0,"speed":1.0,"time":7008,"type":2},{"floorPosition":150.37975,"holdTime":0.0,"positionX":0.0,"speed":1.0,"time":7040,"type":2},{"floorPosition":150.89240000000001,"holdTime":0.0,"positionX":0.0,"speed":1.0,"time":7064,"type":2},{"floorPosition":151.40505999999999,"holdTime":0.0,"positionX":0.0,"speed":1.0,"time":7088,"type":2},{"floorPosition":151.91772,"holdTime":0.0,"positionX":0.0,"speed":1.0,"time":7112,"type":2},{"floorPosition":152.43037000000001,"holdTime":0.0,"positionX":0.0,"speed":1.0,"time":7136,"type":2},{"floorPosition":153.11392000000001,"holdTime":0.0,"positionX":-5.0,"speed":1.0,"time":7168,"type":1},{"floorPosition":153.45569,"holdTime":0.0,"positionX":-5.0,"speed":1.0,"time":7184,"type":1},{"floorPosition":153.79747,"holdTime":0.0,"positionX":4.0,"speed":1.0,"time":7200,"type":1},{"floorPosition":154.13924,"holdTime":0.0,"positionX":-2.0,"speed":1.0,"time":7216,"type":1},{"floorPosition":154.31012000000001,"holdTime":0.0,"positionX":2.0,"speed":1.0,"time":7224,"type":1},{"floorPosition":154.65190000000001,"holdTime":0.0,"positionX":2.0,"speed":1.0,"time":7240,"type":1},{"floorPosition":154.82277999999999,"holdTime":0.0,"positionX":-2.0,"speed":1.0,"time":7248,"type":1},{"floorPosition":155.16454999999999,"holdTime":0.0,"positionX":5.0,"speed":1.0,"time":7264,"type":4},{"floorPosition":155.84809999999999,"holdTime":0.0,"positionX":-5.0,"speed":1.0,"time":7296,"type":1},{"floorPosition":156.53165000000001,"holdTime":0.0,"positionX":-5.0,"speed":1.0,"time":7328,"type":1},{"floorPosition":156.53165000000001,"holdTime":0.0,"positionX":0.0,"speed":1.0,"time":7328,"type":1},{"floorPosition":157.04429999999999,"holdTime":0.0,"positionX":-5.0,"speed":1.0,"time":7352,"type":1},{"floorPosition":157.55696,"holdTime":0.0,"positionX":-5.0,"speed":1.0,"time":7376,"type":1},{"floorPosition":157.89873,"holdTime":0.0,"positionX":-5.0,"speed":1.0,"time":7392,"type":1},{"floorPosition":157.89873,"holdTime":0.0,"positionX":0.0,"speed":1.0,"time":7392,"type":1},{"floorPosition":158.58228,"holdTime":0.0,"positionX":-5.0,"speed":1.0,"time":7424,"type":1},{"floorPosition":158.92403999999999,"holdTime":0.0,"positionX":0.0,"speed":1.0,"time":7440,"type":1},{"floorPosition":159.26581999999999,"holdTime":0.0,"positionX":-5.0,"speed":1.0,"time":7456,"type":1},{"floorPosition":159.77847,"holdTime":0.0,"positionX":-5.0,"speed":1.0,"time":7480,"type":1},{"floorPosition":160.29114000000001,"holdTime":0.0,"positionX":-5.0,"speed":1.0,"time":7504,"type":1},{"floorPosition":160.63290000000001,"holdTime":0.0,"positionX":-5.0,"speed":1.0,"time":7520,"type":1},{"floorPosition":160.63290000000001,"holdTime":0.0,"positionX":5.0,"speed":1.0,"time":7520,"type":1},{"floorPosition":161.31645,"holdTime":0.0,"positionX":5.0,"speed":1.0,"time":7552,"type":1},{"floorPosition":162.0,"holdTime":0.0,"positionX":0.0,"speed":1.0,"time":7584,"type":1},{"floorPosition":162.0,"holdTime":0.0,"positionX":5.0,"speed":1.0,"time":7584,"type":1},{"floorPosition":162.51265000000001,"holdTime":0.0,"positionX":5.0,"speed":1.0,"time":7608,"type":1},{"floorPosition":163.02530999999999,"holdTime":0.0,"positionX":5.0,"speed":1.0,"time":7632,"type":1},{"floorPosition":163.36707999999999,"holdTime":0.0,"positionX":0.0,"speed":1.0,"time":7648,"type":1},{"floorPosition":163.36707999999999,"holdTime":0.0,"positionX":5.0,"speed":1.0,"time":7648,"type":1},{"floorPosition":164.05063000000001,"holdTime":0.0,"positionX":5.0,"speed":1.0,"time":7680,"type":1},{"floorPosition":164.39240000000001,"holdTime":0.0,"positionX":0.0,"speed":1.0,"time":7696,"type":1},{"floorPosition":164.73418000000001,"holdTime":0.0,"positionX":5.0,"speed":1.0,"time":7712,"type":1},{"floorPosition":165.24682999999999,"holdTime":0.0,"positionX":5.0,"speed":1.0,"time":7736,"type":1},{"floorPosition":165.75949,"holdTime":0.0,"positionX":5.0,"speed":1.0,"time":7760,"type":1},{"floorPosition":166.10126,"holdTime":0.0,"positionX":5.0,"speed":1.0,"time":7776,"type":1},{"floorPosition":166.10126,"holdTime":0.0,"positionX":-5.0,"speed":1.0,"time":7776,"type":1},{"floorPosition":166.78479999999999,"holdTime":0.0,"positionX":-5.0,"speed":1.0,"time":7808,"type":1},{"floorPosition":167.46834999999999,"holdTime":0.0,"positionX":-5.0,"speed":1.0,"time":7840,"type":1},{"floorPosition":167.46834999999999,"holdTime":0.0,"positionX":0.0,"speed":1.0,"time":7840,"type":1},{"floorPosition":167.98099999999999,"holdTime":0.0,"positionX":-5.0,"speed":1.0,"time":7864,"type":1},{"floorPosition":168.49367000000001,"holdTime":0.0,"positionX":-5.0,"speed":1.0,"time":7888,"type":1},{"floorPosition":168.83543,"holdTime":0.0,"positionX":-5.0,"speed":1.0,"time":7904,"type":1},{"floorPosition":168.83543,"holdTime":0.0,"positionX":0.0,"speed":1.0,"time":7904,"type":1},{"floorPosition":169.51898,"holdTime":0.0,"positionX":-5.0,"speed":1.0,"time":7936,"type":1},{"floorPosition":169.86075,"holdTime":0.0,"positionX":2.0,"speed":1.0,"time":7952,"type":1},{"floorPosition":170.20253,"holdTime":0.0,"positionX":5.0,"speed":1.0,"time":7968,"type":1},{"floorPosition":170.20253,"holdTime":0.0,"positionX":-5.0,"speed":1.0,"time":7968,"type":1},{"floorPosition":170.71518,"holdTime":0.0,"positionX":-5.0,"speed":1.0,"time":7992,"type":1},{"floorPosition":171.22783999999999,"holdTime":0.0,"positionX":-5.0,"speed":1.0,"time":8016,"type":1},{"floorPosition":171.56961000000001,"holdTime":0.0,"positionX":5.0,"speed":1.0,"time":8032,"type":1},{"floorPosition":171.56961000000001,"holdTime":0.0,"positionX":-5.0,"speed":1.0,"time":8032,"type":1},{"floorPosition":172.25316000000001,"holdTime":0.0,"positionX":5.0,"speed":1.0,"time":8064,"type":1},{"floorPosition":172.9367,"holdTime":0.0,"positionX":5.0,"speed":1.0,"time":8096,"type":1},{"floorPosition":172.9367,"holdTime":0.0,"positionX":-5.0,"speed":1.0,"time":8096,"type":1},{"floorPosition":173.44936000000001,"holdTime":0.0,"positionX":5.0,"speed":1.0,"time":8120,"type":1},{"floorPosition":173.96202,"holdTime":0.0,"positionX":5.0,"speed":1.0,"time":8144,"type":1},{"floorPosition":174.30378999999999,"holdTime":0.0,"positionX":-5.0,"speed":1.0,"time":8160,"type":1},{"floorPosition":174.30378999999999,"holdTime":0.0,"positionX":5.0,"speed":1.0,"time":8160,"type":1},{"floorPosition":174.98733999999999,"holdTime":0.0,"positionX":5.0,"speed":1.0,"time":8192,"type":1},{"floorPosition":175.32911999999999,"holdTime":0.0,"positionX":5.0,"speed":1.0,"time":8208,"type":1},{"floorPosition":175.32911999999999,"holdTime":0.0,"positionX":-2.0,"speed":1.0,"time":8208,"type":1},{"floorPosition":175.67088000000001,"holdTime":0.0,"positionX":-5.0,"speed":1.0,"time":8224,"type":1},{"floorPosition":175.67088000000001,"holdTime":0.0,"positionX":5.0,"speed":1.0,"time":8224,"type":1},{"floorPosition":176.18352999999999,"holdTime":0.0,"positionX":5.0,"speed":1.0,"time":8248,"type":1},{"floorPosition":176.6962,"holdTime":0.0,"positionX":-5.0,"speed":1.0,"time":8272,"type":1},{"floorPosition":177.03796,"holdTime":0.0,"positionX":0.0,"speed":1.0,"time":8288,"type":4},{"floorPosition":177.72150999999999,"holdTime":96.0,"positionX":-5.0,"speed":1.8,"time":8320,"type":3},{"floorPosition":177.72150999999999,"holdTime":96.0,"positionX":5.0,"speed":1.8,"time":8320,"type":3},{"floorPosition":183.18987000000001,"holdTime":0.0,"positionX":-4.0,"speed":1.0,"time":8576,"type":4},{"floorPosition":184.55696,"holdTime":0.0,"positionX":4.0,"speed":1.0,"time":8640,"type":4},{"floorPosition":185.92403999999999,"holdTime":0.0,"positionX":-2.0,"speed":1.0,"time":8704,"type":1},{"floorPosition":186.60758999999999,"holdTime":0.0,"positionX":2.0,"speed":1.0,"time":8736,"type":1},{"floorPosition":187.29114000000001,"holdTime":0.0,"positionX":0.0,"speed":1.0,"time":8768,"type":1},{"floorPosition":187.97469000000001,"holdTime":0.0,"positionX":0.0,"speed":1.0,"time":8800,"type":4},{"floorPosition":188.65822,"holdTime":0.0,"positionX":-5.0,"speed":1.0,"time":8832,"type":1},{"floorPosition":189.0,"holdTime":0.0,"positionX":-1.0,"speed":1.0,"time":8848,"type":1},{"floorPosition":189.34177,"holdTime":0.0,"positionX":-5.0,"speed":1.0,"time":8864,"type":1},{"floorPosition":189.68352999999999,"holdTime":16.0,"positionX":-1.0,"speed":1.8,"time":8880,"type":3},{"floorPosition":190.36707999999999,"holdTime":0.0,"positionX":-4.0,"speed":1.0,"time":8912,"type":1},{"floorPosition":190.70885999999999,"holdTime":0.0,"positionX":-2.0,"speed":1.0,"time":8928,"type":1},{"floorPosition":191.05063000000001,"holdTime":0.0,"positionX":0.0,"speed":1.0,"time":8944,"type":1},{"floorPosition":191.39240000000001,"holdTime":0.0,"positionX":5.0,"speed":1.0,"time":8960,"type":1},{"floorPosition":191.73418000000001,"holdTime":0.0,"positionX":1.0,"speed":1.0,"time":8976,"type":1},{"floorPosition":192.07594,"holdTime":0.0,"positionX":5.0,"speed":1.0,"time":8992,"type":1},{"floorPosition":192.41771,"holdTime":16.0,"positionX":1.0,"speed":1.8,"time":9008,"type":3},{"floorPosition":193.10126,"holdTime":0.0,"positionX":4.0,"speed":1.0,"time":9040,"type":1},{"floorPosition":193.44304,"holdTime":0.0,"positionX":2.0,"speed":1.0,"time":9056,"type":1},{"floorPosition":193.78479999999999,"holdTime":0.0,"positionX":0.0,"speed":1.0,"time":9072,"type":1},{"floorPosition":194.12656999999999,"holdTime":0.0,"positionX":-5.0,"speed":1.0,"time":9088,"type":1},{"floorPosition":194.46834999999999,"holdTime":0.0,"positionX":-2.0,"speed":1.0,"time":9104,"type":1},{"floorPosition":194.81012000000001,"holdTime":0.0,"positionX":2.0,"speed":1.0,"time":9120,"type":1},{"floorPosition":195.15189000000001,"holdTime":16.0,"positionX":5.0,"speed":1.8,"time":9136,"type":3},{"floorPosition":195.83543,"holdTime":0.0,"positionX":2.0,"speed":1.0,"time":9168,"type":1},{"floorPosition":196.17722000000001,"holdTime":0.0,"positionX":-2.0,"speed":1.0,"time":9184,"type":1},{"floorPosition":196.51898,"holdTime":0.0,"positionX":-5.0,"speed":1.0,"time":9200,"type":1},{"floorPosition":196.86075,"holdTime":16.0,"positionX":4.0,"speed":1.8,"time":9216,"type":3},{"floorPosition":197.54429999999999,"holdTime":0.0,"positionX":0.0,"speed":1.0,"time":9248,"type":1},{"floorPosition":197.88607999999999,"holdTime":16.0,"positionX":-4.0,"speed":1.8,"time":9264,"type":3},{"floorPosition":198.56961000000001,"holdTime":0.0,"positionX":4.0,"speed":1.0,"time":9296,"type":1},{"floorPosition":198.91139000000001,"holdTime":0.0,"positionX":0.0,"speed":1.0,"time":9312,"type":1},{"floorPosition":199.25316000000001,"holdTime":0.0,"positionX":-4.0,"speed":1.0,"time":9328,"type":1},{"floorPosition":199.59492,"holdTime":0.0,"positionX":4.0,"speed":1.0,"time":9344,"type":1},{"floorPosition":199.9367,"holdTime":0.0,"positionX":-4.0,"speed":1.0,"time":9360,"type":1},{"floorPosition":200.10758999999999,"holdTime":0.0,"positionX":0.0,"speed":1.0,"time":9368,"type":1},{"floorPosition":200.27847,"holdTime":0.0,"positionX":-4.0,"speed":1.0,"time":9376,"type":1},{"floorPosition":200.62025,"holdTime":0.0,"positionX":4.0,"speed":1.0,"time":9392,"type":1},{"floorPosition":200.62025,"holdTime":0.0,"positionX":-4.0,"speed":1.0,"time":9392,"type":1},{"floorPosition":201.30378999999999,"holdTime":0.0,"positionX":-4.0,"speed":1.0,"time":9424,"type":1},{"floorPosition":201.64556999999999,"holdTime":0.0,"positionX":0.0,"speed":1.0,"time":9440,"type":1},{"floorPosition":201.98733999999999,"holdTime":0.0,"positionX":4.0,"speed":1.0,"time":9456,"type":1},{"floorPosition":202.32910000000001,"holdTime":0.0,"positionX":-4.0,"speed":1.0,"time":9472,"type":1},{"floorPosition":202.67088000000001,"holdTime":0.0,"positionX":4.0,"speed":1.0,"time":9488,"type":1},{"floorPosition":202.84177,"holdTime":0.0,"positionX":0.0,"speed":1.0,"time":9496,"type":1},{"floorPosition":203.01265000000001,"holdTime":0.0,"positionX":4.0,"speed":1.0,"time":9504,"type":1},{"floorPosition":203.35443000000001,"holdTime":0.0,"positionX":-4.0,"speed":1.0,"time":9520,"type":1},{"floorPosition":203.35443000000001,"holdTime":0.0,"positionX":4.0,"speed":1.0,"time":9520,"type":1},{"floorPosition":204.03796,"holdTime":0.0,"positionX":0.0,"speed":1.0,"time":9552,"type":1},{"floorPosition":204.37975,"holdTime":0.0,"positionX":-4.0,"speed":1.0,"time":9568,"type":1},{"floorPosition":204.72150999999999,"holdTime":0.0,"positionX":4.0,"speed":1.0,"time":9584,"type":1},{"floorPosition":205.06327999999999,"holdTime":0.0,"positionX":-5.0,"speed":1.0,"time":9600,"type":1},{"floorPosition":205.40505999999999,"holdTime":0.0,"positionX":-5.0,"speed":1.0,"time":9616,"type":1},{"floorPosition":205.74682999999999,"holdTime":0.0,"positionX":-2.0,"speed":1.0,"time":9632,"type":1},{"floorPosition":206.08860999999999,"holdTime":0.0,"positionX":-2.0,"speed":1.0,"time":9648,"type":1},{"floorPosition":206.43037000000001,"holdTime":0.0,"positionX":2.0,"speed":1.0,"time":9664,"type":1},{"floorPosition":206.77214000000001,"holdTime":0.0,"positionX":2.0,"speed":1.0,"time":9680,"type":1},{"floorPosition":207.11392000000001,"holdTime":0.0,"positionX":5.0,"speed":1.0,"time":9696,"type":1},{"floorPosition":207.45569,"holdTime":0.0,"positionX":5.0,"speed":1.0,"time":9712,"type":1},{"floorPosition":207.79747,"holdTime":48.0,"positionX":-4.0,"speed":1.8,"time":9728,"type":3},{"floorPosition":208.13924,"holdTime":0.0,"positionX":0.0,"speed":1.0,"time":9744,"type":1},{"floorPosition":208.48099999999999,"holdTime":0.0,"positionX":3.0,"speed":1.0,"time":9760,"type":1},{"floorPosition":208.82277999999999,"holdTime":0.0,"positionX":0.0,"speed":1.0,"time":9776,"type":1},{"floorPosition":209.16454999999999,"holdTime":48.0,"positionX":4.0,"speed":1.8,"time":9792,"type":3},{"floorPosition":209.50631999999999,"holdTime":0.0,"positionX":0.0,"speed":1.0,"time":9808,"type":1},{"floorPosition":209.84809999999999,"holdTime":0.0,"positionX":-3.0,"speed":1.0,"time":9824,"type":1},{"floorPosition":210.18987000000001,"holdTime":0.0,"positionX":0.0,"speed":1.0,"time":9840,"type":1},{"floorPosition":210.53165000000001,"holdTime":32.0,"positionX":-4.0,"speed":1.8,"time":9856,"type":3},{"floorPosition":211.21518,"holdTime":0.0,"positionX":-4.0,"speed":1.0,"time":9888,"type":4},{"floorPosition":211.55696,"holdTime":0.0,"positionX":-4.0,"speed":1.0,"time":9904,"type":4},{"floorPosition":211.89873,"holdTime":32.0,"positionX":4.0,"speed":1.8,"time":9920,"type":3},{"floorPosition":212.58228,"holdTime":0.0,"positionX":4.0,"speed":1.0,"time":9952,"type":4},{"floorPosition":212.92403999999999,"holdTime":0.0,"positionX":4.0,"speed":1.0,"time":9968,"type":4},{"floorPosition":213.26581999999999,"holdTime":0.0,"positionX":-4.0,"speed":1.0,"time":9984,"type":1},{"floorPosition":213.60758999999999,"holdTime":0.0,"positionX":0.0,"speed":1.0,"time":10000,"type":1},{"floorPosition":213.94936000000001,"holdTime":0.0,"positionX":-4.0,"speed":1.0,"time":10016,"type":1},{"floorPosition":214.29114000000001,"holdTime":0.0,"positionX":4.0,"speed":1.0,"time":10032,"type":1},{"floorPosition":214.63290000000001,"holdTime":0.0,"positionX":-4.0,"speed":1.0,"time":10048,"type":1},{"floorPosition":214.97467,"holdTime":0.0,"positionX":4.0,"speed":1.0,"time":10064,"type":1},{"floorPosition":215.31645,"holdTime":0.0,"positionX":0.0,"speed":1.0,"time":10080,"type":1},{"floorPosition":215.65822,"holdTime":0.0,"positionX":4.0,"speed":1.0,"time":10096,"type":1},{"floorPosition":216.0,"holdTime":0.0,"positionX":-4.0,"speed":1.0,"time":10112,"type":1},{"floorPosition":216.23497,"holdTime":0.0,"positionX":-4.0,"speed":1.0,"time":10123,"type":1},{"floorPosition":216.44855999999999,"holdTime":0.0,"positionX":-4.0,"speed":1.0,"time":10133,"type":1},{"floorPosition":216.68352999999999,"holdTime":0.0,"positionX":-4.0,"speed":1.0,"time":10144,"type":1},{"floorPosition":217.36707999999999,"holdTime":0.0,"positionX":4.0,"speed":1.0,"time":10176,"type":1},{"floorPosition":217.60204999999999,"holdTime":0.0,"positionX":4.0,"speed":1.0,"time":10187,"type":1},{"floorPosition":217.81566000000001,"holdTime":0.0,"positionX":4.0,"speed":1.0,"time":10197,"type":1},{"floorPosition":218.05063000000001,"holdTime":0.0,"positionX":4.0,"speed":1.0,"time":10208,"type":1},{"floorPosition":218.73418000000001,"holdTime":0.0,"positionX":-4.0,"speed":1.0,"time":10240,"type":1},{"floorPosition":218.96915000000001,"holdTime":0.0,"positionX":1.0,"speed":1.0,"time":10251,"type":1},{"floorPosition":219.18275,"holdTime":0.0,"positionX":-1.0,"speed":1.0,"time":10261,"type":1},{"floorPosition":219.41771,"holdTime":0.0,"positionX":4.0,"speed":1.0,"time":10272,"type":1},{"floorPosition":219.65268,"holdTime":0.0,"positionX":-4.0,"speed":1.0,"time":10283,"type":1},{"floorPosition":219.86628999999999,"holdTime":0.0,"positionX":4.0,"speed":1.0,"time":10293,"type":1},{"floorPosition":220.10126,"holdTime":64.0,"positionX":0.0,"speed":1.8,"time":10304,"type":3},{"floorPosition":221.46834999999999,"holdTime":0.0,"positionX":0.0,"speed":1.0,"time":10368,"type":4}],"notesBelow":[{"floorPosition":92.962019999999995,"holdTime":64.0,"positionX":0.0,"speed":1.8,"time":4352,"type":3},{"floorPosition":180.45569,"holdTime":96.0,"positionX":-5.0,"speed":1.8,"time":8448,"type":3},{"floorPosition":180.45569,"holdTime":96.0,"positionX":5.0,"speed":1.8,"time":8448,"type":3}],"speedEvents":[{"endTime":1000000000.0,"startTime":0.0,"value":1.8}]},{"bpm":158.0,"judgeLineDisappearEvents":[{"easing":0,"end":0.0,"endTime":10368.0,"start":0.0,"startTime":0.0},{"easing":0,"end":0.0,"endTime":10496.0,"start":1.0,"startTime":10368.0},{"easing":0,"end":0.0,"endTime":1000000000.0,"start":0.0,"startTime":10496.0}],"judgeLineMoveXEvents":[{"easing":0,"end":0.5,"endTime":10368.0,"start":0.5,"startTime":0.0},{"easing":0,"end":0.5,"endTime":10496.0,"start":0.5,"startTime":10368.0},{"easing":0,"end":0.5,"endTime":1000000000.0,"start":0.5,"startTime":10496.0}],"judgeLineMoveYEvents":[{"easing":0,"end":0.5,"endTime":10368.0,"start":0.5,"startTime":0.0},{"easing":6,"end":1.0,"endTime":10496.0,"start":0.5,"startTime":10368.0},{"easing":0,"end":1.0,"endTime":1000000000.0,"start":1.0,"startTime":10496.0}],"judgeLineRotateEvents":[{"easing":0,"end":0.0,"endTime":1000000000.0,"start":0.0,"startTime":0.0}],"notesAbove":[],"notesBelow":[],"speedEvents":[{"endTime":1000000000.0,"startTime":0.0,"value":1.0}]}],"offset":0.0}
